Workbook

Sheet Paper LBO - Template
C2: Dynacast LBO - Summer 2025
C3: ($ in millions) | D3: Assumptions
C5: Entry Assumptions
C6: EV Multiple | D6: 8.9
C7: EBITDA | D7: =D30 -> 123.5
C8: Enterprise Value | D8: =D6*D7 -> 1099.15
C9: Existing Debt | D9: 486
C10: Implied Value of Equity | D10: =D8-D9 -> 613.15
C11: Holding Period | D11: 5
C12: Max Leverage | D12: 4.25
C13: Mgmt. Rollover | D13: 0.05
C14: Est. Txn Fees & Exp (% of TEV) | D14: 0.03
C16: Sources and Uses
C18: Sources | F18: Uses | K18: 45555
C19: Revolver | D19: 0 | F19: Consideration to Equity Holders | I19: =D10 -> 613.15 | K19: 3M SOFR | L19: Spread
C20: Term Loan B | D20: =$D$12*$D$7 -> 524.875 | F20: Refi Existing Debt | I20: =D9 -> 486 | K20: 0.0533 | L20: 0.0425
C21: Mgmt. Rollover | D21: =$D$10*$D$13 -> 30.6575 | F21: Est. Txn Fees & Expenses | I21: =$D$8*$D$14 -> 32.9745 | K21: 0.0533 | L21: 0.0475
C22: Sponsor Equity Check | D22: =D23-SUM(D19:D21) -> 576.592
C23: Total Sources | D23: =I23 -> 1132.1245 | F23: Total Uses | I23: =I19+I20+I21 -> 1132.1245
D26: PF LTM Sep | E26: Projected
C27: Simple P&L | D27: 2014 | E27: =D27+1 -> 2015 | F27: =+E27+1 -> 2016 | G27: =+F27+1 -> 2017 | H27: =+G27+1 -> 2018 | I27: =+H27+1 -> 2019
C28: Revenue | D28: 650 | E28: =D28*(1+E29) -> 708.5 | F28: =E28*(1+F29) -> 772.265 | G28: =F28*(1+G29) -> 841.76885 | H28: =G28*(1+H29) -> 917.52805 | I28: =H28*(1+I29) -> 1000.1056
C29: % Growth | D29: 0.081 | E29: 0.09 | F29: 0.09 | G29: 0.09 | H29: 0.09 | I29: 0.09
C30: EBITDA | D30: 123.5 | E30: =E28*E31 -> 141.7 | F30: =F28*F31 -> 162.17565 | G30: =G28*G31 -> 176.77146 | H30: =H28*H31 -> 192.68089 | I30: =I28*I31 -> 210.02217
C31: % Margin | D31: =D30/D28 -> 0.19 | E31: 0.2 | F31: 0.21 | G31: 0.21 | H31: 0.21 | I31: 0.21
C32: D&A | D32: 30 | E32: =E44 -> 32.7 | F32: =F44 -> 35.643 | G32: =G44 -> 38.85087 | H32: =H44 -> 42.347448 | I32: =I44 -> 46.158719
C33: % Of Capex | D33: =D32/$D$44 -> 1 | E33: =E32/E44 -> 1 | F33: =F32/F44 -> 1 | G33: =G32/G44 -> 1 | H33: =H32/H44 -> 1 | I33: =I32/I44 -> 1
C34: EBIT | D34: 74.8 | E34: =E30-E32 -> 109 | F34: =F30-F32 -> 126.53265 | G34: =G30-G32 -> 137.92059 | H34: =H30-H32 -> 150.33344 | I34: =I30-I32 -> 163.86345
C35: % Margin | D35: =D34/D28 -> 0.11507692 | E35: =E34/E28 -> 0.15384615 | F35: =F34/F28 -> 0.16384615 | G35: =G34/G28 -> 0.16384615 | H35: =H34/H28 -> 0.16384615 | I35: =I34/I28 -> 0.16384615
C36: Net Interest Expense | D36: -- | E36: =E63 -> 50.939749 | F36: =F63 -> 46.182315 | G36: =G63 -> 39.959327 | H36: =H63 -> 32.36076 | I36: =I63 -> 23.19874
C37: EBT | D37: 23.4 | E37: =E34-E36 -> 58.060251 | F37: =F34-F36 -> 80.350335 | G37: =G34-G36 -> 97.961262 | H37: =H34-H36 -> 117.97268 | I37: =I34-I36 -> 140.66471
C38: Income Tax Expense | D38: -- | E38: =E37*E54 -> 14.515063 | F38: =F37*F54 -> 20.087584 | G38: =G37*G54 -> 24.490315 | H38: =H37*H54 -> 29.49317 | I38: =I37*I54 -> 35.166178
C39: Net Income | D39: 10.5 | E39: =E37-E38 -> 43.545188 | F39: =F37-F38 -> 60.262751 | G39: =G37-G38 -> 73.470946 | H39: =H37-H38 -> 88.479511 | I39: =I37-I38 -> 105.49853
C40: % Margin | D40: =D39/D28 -> 0.016153846 | E40: =E39/E28 -> 0.061461098 | F40: =F39/F28 -> 0.078033772 | G40: =G39/G28 -> 0.087281617 | H40: =H39/H28 -> 0.096432486 | I40: =I39/I28 -> 0.1054874
D41: PF LTM | E41: Projected
C42: Simple FCF Build | D42: 2014 | E42: =D42+1 -> 2015 | F42: =+E42+1 -> 2016 | G42: =+F42+1 -> 2017 | H42: =+G42+1 -> 2018 | I42: =+H42+1 -> 2019
C43: EBITDA | D43: =D30 -> 123.5 | E43: =E30 -> 141.7 | F43: =F30 -> 162.17565 | G43: =G30 -> 176.77146 | H43: =H30 -> 192.68089 | I43: =I30 -> 210.02217
C44: Capex | D44: 30 | E44: =E28*$E$50 -> 32.7 | F44: =F28*$E$50 -> 35.643 | G44: =G28*$E$50 -> 38.85087 | H44: =H28*$E$50 -> 42.347448 | I44: =I28*$E$50 -> 46.158719
C45: Net Change in WC | D45: -- | E45: =E53-D53 -> 4.5045 | F45: =F53-E53 -> 4.909905 | G45: =G53-F53 -> 5.3517965 | H45: =H53-G53 -> 5.8334581 | I45: =I53-H53 -> 6.3584694
C46: Interest | D46: -- | E46: =E36 -> 50.939749 | F46: =F36 -> 46.182315 | G46: =G36 -> 39.959327 | H46: =H36 -> 32.36076 | I46: =I36 -> 23.19874
C47: Taxes | D47: -- | E47: =E38 -> 14.515063 | F47: =F38 -> 20.087584 | G47: =G38 -> 24.490315 | H47: =H38 -> 29.49317 | I47: =I38 -> 35.166178
C48: LFCF | D48: -- | E48: =E43-SUM(E44:E47) -> 39.040688 | F48: =F43-SUM(F44:F47) -> 55.352846 | G48: =G43-SUM(G44:G47) -> 68.11915 | H48: =H43-SUM(H44:H47) -> 82.646053 | I48: =I43-SUM(I44:I47) -> 99.140064
C50: Capex as % of Revenue | D50: =$D$44/$D$28 -> 0.046153846 | E50: 0.046153846 | F50: 0.046153846 | G50: 0.046153846 | H50: 0.046153846 | I50: 0.046153846
C51: D&A as a % of Capex | D51: =D32/D44 -> 1 | E51: 1 | F51: 1 | G51: 1 | H51: 1 | I51: 1
C52: NWC as a % of Revenue | D52: =D53/D28 -> 0.077 | E52: 0.077 | F52: 0.077 | G52: 0.077 | H52: 0.077 | I52: 0.077
C53: NWC $ | D53: 50.05 | E53: =E52*E28 -> 54.5545 | F53: =F52*F28 -> 59.464405 | G53: =G52*G28 -> 64.816201 | H53: =H52*H28 -> 70.64966 | I53: =I52*I28 -> 77.008129
C54: Income Tax Rate | D54: -- | E54: 0.25 | F54: 0.25 | G54: 0.25 | H54: 0.25 | I54: 0.25
D55: PF | E55: Projected
C56: Term Loan Pay Down | D56: 2014 | E56: =D56+1 -> 2015 | F56: =+E56+1 -> 2016 | G56: =+F56+1 -> 2017 | H56: =+G56+1 -> 2018 | I56: =+H56+1 -> 2019
C57: BOP | E57: =D59 -> 524.875 | F57: =E59 -> 485.83431 | G57: =F59 -> 430.48147 | H57: =G59 -> 362.36232 | I57: =H59 -> 279.71626
C58: Paydown | E58: =(IF(E48<0,0,-MIN(E57,E48))) -> -39.040688 | F58: =(IF(F48<0,0,-MIN(F57,F48))) -> -55.352846 | G58: =(IF(G48<0,0,-MIN(G57,G48))) -> -68.11915 | H58: =(IF(H48<0,0,-MIN(H57,H48))) -> -82.646053 | I58: =(IF(I48<0,0,-MIN(I57,I48))) -> -99.140064
C59: EOP | D59: =$D$20 -> 524.875 | E59: =E57+E58 -> 485.83431 | F59: =F57+F58 -> 430.48147 | G59: =G57+G58 -> 362.36232 | H59: =H57+H58 -> 279.71626 | I59: =I57+I58 -> 180.5762
C60: Gross Leverage | D60: =D59/D43 -> 4.25 | E60: =E59/E43 -> 3.4286119 | F60: =F59/F43 -> 2.6544149 | G60: =G59/G43 -> 2.0498915 | H60: =H59/H43 -> 1.4517073 | I60: =I59/I43 -> 0.85979589
C62: Average Balance | E62: =AVERAGE(E57,E59) -> 505.35466 | F62: =AVERAGE(F57,F59) -> 458.15789 | G62: =AVERAGE(G57,G59) -> 396.42189 | H62: =AVERAGE(H57,H59) -> 321.03929 | I62: =AVERAGE(I57,I59) -> 230.14623
C63: All-In Interest Expense | E63: =E62*($K$21+$L$21) -> 50.939749 | F63: =F62*($K$21+$L$21) -> 46.182315 | G63: =G62*($K$21+$L$21) -> 39.959327 | H63: =H62*($K$21+$L$21) -> 32.36076 | I63: =I62*($K$21+$L$21) -> 23.19874
C66: Exit Assumptions and Calculations
C67: EV Multiple | D67: 8.9
C68: EBITDA | D68: =$I$43 -> 210.02217
C69: TEV | D69: =D67*D68 -> 1869.1973
C70: Existing Debt | D70: =I59 -> 180.5762
C71: Est. Txn Fees & Expenses | D71: =$E$71*$D$69 -> 56.075919 | E71: 0.03
C72: Consideration to Equity Holders @ Exit | D72: =D69-D70-D71 -> 1632.5452
C73: Sponsor Ownership % | D73: 0.9
C74: Sponsor Equity Proceeds @ Exit | D74: =D72*D73 -> 1469.2907
C75: Sponsor Equity Check @ Entry | D75: =$D$22 -> 576.592
C77: MOIC | D77: =D74/D75 -> 2.5482328
C78: IRR | D78: =D77^(1/5)-1 -> 0.20572377
C80: Quick IRR Calc Method
C81: =MOIC^(1 / Investment Period) -1
C84: Approach & Best Practices
C85: At this stage in a process you are far less concerned about validating the underlying operating assumptions and far more focused on making sure the "quick & dirty" returns remotely work. Less is more at this stage - you don't need to get super granular on the structure, fees etc. Keep it so simple that you could do this on a napkin. Best practices: format & hardcode the key cells that drive the analysis first. After you have the drivers in place, begin linking / calculating the rest. No need to have a bunch of complex calcs here, you want to be able to quickly toggle your assumptions with ease.
C86: Paper LBO Steps & Notes
C87: 1) Input the entry assumptions. Note - For simplicity, you don't have to account for the existing debt at this stage (cash free & debt free). However, if you have the info, its worth including.
C88: 2) Solve for Equity Purchase Price
C89: 3) Set up the S&U. Note - For a paper LBO, no need to get fancy on the cap structure and fees. Keep it simple and just assume a max leverage multiple and cost of debt (don't worry about OID or other fees on the debt). Make new sponsor equity the plug for the S&U.
C90: 4) Set up the "simple" P&L. Note - Set up the key P&L driver assumptions (revenue & margins) and leave interest expense blank at this stage
C91: 5) Set up the "simple" FCF build. Note - Continue to keep interest expense blank and input the key driver assumptions for FCF (Capex, D&A, NWC, Tax Rate)
C92: 6) Set up the debt paydown table and keep the assumptions super high level (don’t worry about the revolver funding losses, assume 100% of FCF is used to repay debt, don't need to account for the term loan amort at this stage).
C93: 7) Calculate interest expense and link the #"s back to the P&L and FCF build
... C96: 10) Tick and tie the #'s to ensure all calcs are correct

Sheet Bull Case
C2: Dynacast LBO - Bull Case ($ in millions)
C3: ($ in millions) | D3: Assumptions
C4: BULL CASE - scenario tab. Changed inputs shaded yellow (blue font). Sources and rationale in rows 99+.
C5: Entry Assumptions
C6: EV Multiple | D6: 8.9
C7: EBITDA | D7: =D30 -> 123.5
C8: Enterprise Value | D8: =D6*D7 -> 1099.15
C9: Existing Debt | D9: 486
C10: Implied Value of Equity | D10: =D8-D9 -> 613.15
C11: Holding Period | D11: 5
C12: Max Leverage | D12: 4.25
C13: Mgmt. Rollover | D13: 0.05
C14: Est. Txn Fees & Exp (% of TEV) | D14: 0.03
C16: Sources and Uses
C18: Sources | F18: Uses | K18: 45555
C19: Revolver | D19: 0 | F19: Consideration to Equity Holders | I19: =D10 -> 613.15 | K19: 3M SOFR | L19: Spread
C20: Term Loan B | D20: =$D$12*$D$7 -> 524.875 | F20: Refi Existing Debt | I20: =D9 -> 486 | K20: 0.0533 | L20: 0.0425
C21: Mgmt. Rollover | D21: =$D$10*$D$13 -> 30.6575 | F21: Est. Txn Fees & Expenses | I21: =$D$8*$D$14 -> 32.9745 | K21: 0.0533 | L21: 0.0475
C22: Sponsor Equity Check | D22: =D23-SUM(D19:D21) -> 576.592
C23: Total Sources | D23: =I23 -> 1132.1245 | F23: Total Uses | I23: =I19+I20+I21 -> 1132.1245
D26: PF LTM Sep | E26: Projected
C27: Simple P&L | D27: 2014 | E27: =D27+1 -> 2015 | F27: =+E27+1 -> 2016 | G27: =+F27+1 -> 2017 | H27: =+G27+1 -> 2018 | I27: =+H27+1 -> 2019
C28: Revenue | D28: 650 | E28: =D28*(1+E29) -> 727.35 | F28: =E28*(1+F29) -> 813.90465 | G28: =F28*(1+G29) -> 910.7593 | H28: =G28*(1+H29) -> 1019.1397 | I28: =H28*(1+I29) -> 1140.4173
C29: % Growth | D29: 0.081 | E29: 0.119 | F29: 0.119 | G29: 0.119 | H29: 0.119 | I29: 0.119
C30: EBITDA | D30: 123.5 | E30: =E28*E31 -> 149.10675 | F30: =F28*F31 -> 174.9895 | G30: =G28*G31 -> 195.81325 | H30: =H28*H31 -> 219.11503 | I30: =I28*I31 -> 245.18972
C31: % Margin | D31: =D30/D28 -> 0.19 | E31: 0.205 | F31: 0.215 | G31: 0.215 | H31: 0.215 | I31: 0.215
C32: D&A | D32: 30 | E32: =E44 -> 33.57 | F32: =F44 -> 37.56483 | G32: =G44 -> 42.035045 | H32: =H44 -> 47.037215 | I32: =I44 -> 52.634644
C33: % Of Capex | D33: =D32/$D$44 -> 1 | E33: =E32/E44 -> 1 | F33: =F32/F44 -> 1 | G33: =G32/G44 -> 1 | H33: =H32/H44 -> 1 | I33: =I32/I44 -> 1
C34: EBIT | D34: 74.8 | E34: =E30-E32 -> 115.53675 | F34: =F30-F32 -> 137.42467 | G34: =G30-G32 -> 153.77821 | H34: =H30-H32 -> 172.07781 | I34: =I30-I32 -> 192.55507
C35: % Margin | D35: =D34/D28 -> 0.11507692 | E35: =E34/E28 -> 0.15884615 | F35: =F34/F28 -> 0.16884615 | G35: =G34/G28 -> 0.16884615 | H35: =H34/H28 -> 0.16884615 | I35: =I34/I28 -> 0.16884615
C36: Net Interest Expense | D36: -- | E36: =E63 -> 50.75898 | F36: =F63 -> 45.470598 | G36: =G63 -> 38.34306 | H36: =H63 -> 29.382194 | I36: =I63 -> 18.29243
C37: EBT | D37: 23.4 | E37: =E34-E36 -> 64.77777 | F37: =F34-F36 -> 91.954075 | G37: =G34-G36 -> 115.43516 | H37: =H34-H36 -> 142.69565 | I37: =I34-I36 -> 174.26272
C38: Income Tax Expense | D38: -- | E38: =E37*E54 -> 16.194443 | F38: =F37*F54 -> 22.988519 | G38: =G37*G54 -> 28.858789 | H38: =H37*H54 -> 35.673912 | I38: =I37*I54 -> 43.565679
C39: Net Income | D39: 10.5 | E39: =E37-E38 -> 48.583328 | F39: =F37-F38 -> 68.965556 | G39: =G37-G38 -> 86.576367 | H39: =H37-H38 -> 107.02174 | I39: =I37-I38 -> 130.69704
C40: % Margin | D40: =D39/D28 -> 0.016153846 | E40: =E39/E28 -> 0.066794979 | F40: =F39/F28 -> 0.084734196 | G40: =G39/G28 -> 0.095059547 | H40: =H39/H28 -> 0.10501185 | I40: =I39/I28 -> 0.11460457
D41: PF LTM | E41: Projected
C42: Simple FCF Build | D42: 2014 | E42: =D42+1 -> 2015 | F42: =+E42+1 -> 2016 | G42: =+F42+1 -> 2017 | H42: =+G42+1 -> 2018 | I42: =+H42+1 -> 2019
C43: EBITDA | D43: =D30 -> 123.5 | E43: =E30 -> 149.10675 | F43: =F30 -> 174.9895 | G43: =G30 -> 195.81325 | H43: =H30 -> 219.11503 | I43: =I30 -> 245.18972
C44: Capex | D44: 30 | E44: =E28*$E$50 -> 33.57 | F44: =F28*$E$50 -> 37.56483 | G44: =G28*$E$50 -> 42.035045 | H44: =H28*$E$50 -> 47.037215 | I44: =I28*$E$50 -> 52.634644
C45: Net Change in WC | D45: -- | E45: =E53-D53 -> 5.95595 | F45: =F53-E53 -> 6.6647081 | G45: =G53-F53 -> 7.4578083 | H45: =H53-G53 -> 8.3452875 | I45: =I53-H53 -> 9.3383767
C46: Interest | D46: -- | E46: =E36 -> 50.75898 | F46: =F36 -> 45.470598 | G46: =G36 -> 38.34306 | H46: =H36 -> 29.382194 | I46: =I36 -> 18.29243
C47: Taxes | D47: -- | E47: =E38 -> 16.194443 | F47: =F38 -> 22.988519 | G47: =G38 -> 28.858789 | H47: =H38 -> 35.673912 | I47: =I38 -> 43.565679
C48: LFCF | D48: -- | E48: =E43-SUM(E44:E47) -> 42.627377 | F48: =F43-SUM(F44:F47) -> 62.300845 | G48: =G43-SUM(G44:G47) -> 79.118548 | H48: =H43-SUM(H44:H47) -> 98.676418 | I48: =I43-SUM(I44:I47) -> 121.35859
C50: Capex as % of Revenue | D50: =$D$44/$D$28 -> 0.046153846 | E50: 0.046153846 | F50: 0.046153846 | G50: 0.046153846 | H50: 0.046153846 | I50: 0.046153846
C51: D&A as a % of Capex | D51: =D32/D44 -> 1 | E51: 1 | F51: 1 | G51: 1 | H51: 1 | I51: 1
C52: NWC as a % of Revenue | D52: =D53/D28 -> 0.077 | E52: 0.077 | F52: 0.077 | G52: 0.077 | H52: 0.077 | I52: 0.077
C53: NWC $ | D53: 50.05 | E53: =E52*E28 -> 56.00595 | F53: =F52*F28 -> 62.670658 | G53: =G52*G28 -> 70.128466 | H53: =H52*H28 -> 78.473754 | I53: =I52*I28 -> 87.812131
C54: Income Tax Rate | D54: -- | E54: 0.25 | F54: 0.25 | G54: 0.25 | H54: 0.25 | I54: 0.25
D55: PF | E55: Projected
C56: Term Loan Pay Down | D56: 2014 | E56: =D56+1 -> 2015 | F56: =+E56+1 -> 2016 | G56: =+F56+1 -> 2017 | H56: =+G56+1 -> 2018 | I56: =+H56+1 -> 2019
C57: BOP | E57: =D59 -> 524.875 | F57: =E59 -> 482.24762 | G57: =F59 -> 419.94678 | H57: =G59 -> 340.82823 | I57: =H59 -> 242.15181
C58: Paydown | E58: =(IF(E48<0,0,-MIN(E57,E48))) -> -42.627377 | F58: =(IF(F48<0,0,-MIN(F57,F48))) -> -62.300845 | G58: =(IF(G48<0,0,-MIN(G57,G48))) -> -79.118548 | H58: =(IF(H48<0,0,-MIN(H57,H48))) -> -98.676418 | I58: =(IF(I48<0,0,-MIN(I57,I48))) -> -121.35859
C59: EOP | D59: =$D$20 -> 524.875 | E59: =E57+E58 -> 482.24762 | F59: =F57+F58 -> 419.94678 | G59: =G57+G58 -> 340.82823 | H59: =H57+H58 -> 242.15181 | I59: =I57+I58 -> 120.79323
C60: Gross Leverage | D60: =D59/D43 -> 4.25 | E60: =E59/E43 -> 3.2342441 | F60: =F59/F43 -> 2.3998399 | G60: =G59/G43 -> 1.740578 | H60: =H59/H43 -> 1.1051356 | I60: =I59/I43 -> 0.49265209
C62: Average Balance | E62: =AVERAGE(E57,E59) -> 503.56131 | F62: =AVERAGE(F57,F59) -> 451.0972 | G62: =AVERAGE(G57,G59) -> 380.3875 | H62: =AVERAGE(H57,H59) -> 291.49002 | I62: =AVERAGE(I57,I59) -> 181.47252
C63: All-In Interest Expense | E63: =E62*($K$21+$L$21) -> 50.75898 | F63: =F62*($K$21+$L$21) -> 45.470598 | G63: =G62*($K$21+$L$21) -> 38.34306 | H63: =H62*($K$21+$L$21) -> 29.382194 | I63: =I62*($K$21+$L$21) -> 18.29243
C66: Exit Assumptions and Calculations
C67: EV Multiple | D67: 10.1
C68: EBITDA | D68: =$I$43 -> 245.18972
C69: TEV | D69: =D67*D68 -> 2476.4161
C70: Existing Debt | D70: =I59 -> 120.79323
C71: Est. Txn Fees & Expenses | D71: =$E$71*$D$69 -> 74.292484 | E71: 0.03
C72: Consideration to Equity Holders @ Exit | D72: =D69-D70-D71 -> 2281.3304
C73: Sponsor Ownership % | D73: 0.9
C74: Sponsor Equity Proceeds @ Exit | D74: =D72*D73 -> 2053.1974
C75: Sponsor Equity Check @ Entry | D75: =$D$22 -> 576.592
C77: MOIC | D77: =D74/D75 -> 3.5609189
C78: IRR | D78: =D77^(1/5)-1 -> 0.28917661
C80: Quick IRR Calc Method
C81: =MOIC^(1 / Investment Period) -1
C84: Approach & Best Practices
C85: At this stage in a process you are far less concerned about validating the underlying operating assumptions and far more focused on making sure the "quick & dirty" returns remotely work. Less is more at this stage - you don't need to get super granular on the structure, fees etc. Keep it so simple that you could do this on a napkin. Best practices: format & hardcode the key cells that drive the analysis first. After you have the drivers in place, begin linking / calculating the rest. No need to have a bunch of complex calcs here, you want to be able to quickly toggle your assumptions with ease.
C86: Paper LBO Steps & Notes
C87: 1) Input the entry assumptions. Note - For simplicity, you don't have to account for the existing debt at this stage (cash free & debt free). However, if you have the info, its worth including.
C88: 2) Solve for Equity Purchase Price
C89: 3) Set up the S&U. Note - For a paper LBO, no need to get fancy on the cap structure and fees. Keep it simple and just assume a max leverage multiple and cost of debt (don't worry about OID or other fees on the debt). Make new sponsor equity the plug for the S&U.
C90: 4) Set up the "simple" P&L. Note - Set up the key P&L driver assumptions (revenue & margins) and leave interest expense blank at this stage
C91: 5) Set up the "simple" FCF build. Note - Continue to keep interest expense blank and input the key driver assumptions for FCF (Capex, D&A, NWC, Tax Rate)
C92: 6) Set up the debt paydown table and keep the assumptions super high level (don’t worry about the revolver funding losses, assume 100% of FCF is used to repay debt, don't need to account for the term loan amort at this stage).
C93: 7) Calculate interest expense and link the #"s back to the P&L and FCF build
... C109: Note: model requires iterative calculation (File > Options > Formulas > Enable iterative calculation); this file is saved with it enabled.

Sheet Bear Case
C2: Dynacast LBO - Bear Case ($ in millions)
C3: ($ in millions) | D3: Assumptions
C4: BEAR CASE - scenario tab. Changed inputs shaded yellow (blue font). Sources and rationale in rows 99+.
C5: Entry Assumptions
C6: EV Multiple | D6: 8.9
C7: EBITDA | D7: =D30 -> 123.5
C8: Enterprise Value | D8: =D6*D7 -> 1099.15
C9: Existing Debt | D9: 486
C10: Implied Value of Equity | D10: =D8-D9 -> 613.15
C11: Holding Period | D11: 5
C12: Max Leverage | D12: 4.25
C13: Mgmt. Rollover | D13: 0.05
C14: Est. Txn Fees & Exp (% of TEV) | D14: 0.03
C16: Sources and Uses
C18: Sources | F18: Uses | K18: 45555
C19: Revolver | D19: 0 | F19: Consideration to Equity Holders | I19: =D10 -> 613.15 | K19: 3M SOFR | L19: Spread
C20: Term Loan B | D20: =$D$12*$D$7 -> 524.875 | F20: Refi Existing Debt | I20: =D9 -> 486 | K20: 0.0533 | L20: 0.0425
C21: Mgmt. Rollover | D21: =$D$10*$D$13 -> 30.6575 | F21: Est. Txn Fees & Expenses | I21: =$D$8*$D$14 -> 32.9745 | K21: 0.0533 | L21: 0.0475
C22: Sponsor Equity Check | D22: =D23-SUM(D19:D21) -> 576.592
C23: Total Sources | D23: =I23 -> 1132.1245 | F23: Total Uses | I23: =I19+I20+I21 -> 1132.1245
D26: PF LTM Sep | E26: Projected
C27: Simple P&L | D27: 2014 | E27: =D27+1 -> 2015 | F27: =+E27+1 -> 2016 | G27: =+F27+1 -> 2017 | H27: =+G27+1 -> 2018 | I27: =+H27+1 -> 2019
C28: Revenue | D28: 650 | E28: =D28*(1+E29) -> 702 | F28: =E28*(1+F29) -> 758.16 | G28: =F28*(1+G29) -> 818.8128 | H28: =G28*(1+H29) -> 884.31782 | I28: =H28*(1+I29) -> 955.06325
C29: % Growth | D29: 0.081 | E29: 0.08 | F29: 0.08 | G29: 0.08 | H29: 0.08 | I29: 0.08
C30: EBITDA | D30: 123.5 | E30: =E28*E31 -> 136.89 | F30: =F28*F31 -> 147.8412 | G30: =G28*G31 -> 159.6685 | H30: =H28*H31 -> 172.44198 | I30: =I28*I31 -> 186.23733
C31: % Margin | D31: =D30/D28 -> 0.19 | E31: 0.195 | F31: 0.195 | G31: 0.195 | H31: 0.195 | I31: 0.195
C32: D&A | D32: 30 | E32: =E44 -> 32.4 | F32: =F44 -> 34.992 | G32: =G44 -> 37.79136 | H32: =H44 -> 40.814669 | I32: =I44 -> 44.079842
C33: % Of Capex | D33: =D32/$D$44 -> 1 | E33: =E32/E44 -> 1 | F33: =F32/F44 -> 1 | G33: =G32/G44 -> 1 | H33: =H32/H44 -> 1 | I33: =I32/I44 -> 1
C34: EBIT | D34: 74.8 | E34: =E30-E32 -> 104.49 | F34: =F30-F32 -> 112.8492 | G34: =G30-G32 -> 121.87714 | H34: =H30-H32 -> 131.62731 | I34: =I30-I32 -> 142.15749
C35: % Margin | D35: =D34/D28 -> 0.11507692 | E35: =E34/E28 -> 0.14884615 | F35: =F34/F28 -> 0.14884615 | G35: =G34/G28 -> 0.14884615 | H35: =H34/H28 -> 0.14884615 | I35: =I34/I28 -> 0.14884615
C36: Net Interest Expense | D36: -- | E36: =E63 -> 51.090708 | F36: =F63 -> 47.002975 | G36: =G63 -> 41.945915 | H36: =H63 -> 35.791514 | I36: =I63 -> 28.397555
C37: EBT | D37: 23.4 | E37: =E34-E36 -> 53.399291 | F37: =F34-F36 -> 65.846222 | G37: =G34-G36 -> 79.93121 | H37: =H34-H36 -> 95.835758 | I37: =I34-I36 -> 113.75985
C38: Income Tax Expense | D38: -- | E38: =E37*E54 -> 13.349823 | F38: =F37*F54 -> 16.461556 | G38: =G37*G54 -> 19.982802 | H38: =H37*H54 -> 23.95894 | I38: =I37*I54 -> 28.439963
C39: Net Income | D39: 10.5 | E39: =E37-E38 -> 40.049468 | F39: =F37-F38 -> 49.384667 | G39: =G37-G38 -> 59.948407 | H39: =H37-H38 -> 71.876819 | I39: =I37-I38 -> 85.319889
C40: % Margin | D40: =D39/D28 -> 0.016153846 | E40: =E39/E28 -> 0.057050525 | F40: =F39/F28 -> 0.065137526 | G40: =G39/G28 -> 0.073213813 | H40: =H39/H28 -> 0.081279396 | I40: =I39/I28 -> 0.089334281
D41: PF LTM | E41: Projected
C42: Simple FCF Build | D42: 2014 | E42: =D42+1 -> 2015 | F42: =+E42+1 -> 2016 | G42: =+F42+1 -> 2017 | H42: =+G42+1 -> 2018 | I42: =+H42+1 -> 2019
C43: EBITDA | D43: =D30 -> 123.5 | E43: =E30 -> 136.89 | F43: =F30 -> 147.8412 | G43: =G30 -> 159.6685 | H43: =H30 -> 172.44198 | I43: =I30 -> 186.23733
C44: Capex | D44: 30 | E44: =E28*$E$50 -> 32.4 | F44: =F28*$E$50 -> 34.992 | G44: =G28*$E$50 -> 37.79136 | H44: =H28*$E$50 -> 40.814669 | I44: =I28*$E$50 -> 44.079842
C45: Net Change in WC | D45: -- | E45: =E53-D53 -> 4.004 | F45: =F53-E53 -> 4.32432 | G45: =G53-F53 -> 4.6702656 | H45: =H53-G53 -> 5.0438868 | I45: =I53-H53 -> 5.4473978
C46: Interest | D46: -- | E46: =E36 -> 51.090708 | F46: =F36 -> 47.002975 | G46: =G36 -> 41.945915 | H46: =H36 -> 35.791514 | I46: =I36 -> 28.397555
C47: Taxes | D47: -- | E47: =E38 -> 13.349823 | F47: =F38 -> 16.461556 | G47: =G38 -> 19.982802 | H47: =H38 -> 23.95894 | I47: =I38 -> 28.439963
C48: LFCF | D48: -- | E48: =E43-SUM(E44:E47) -> 36.045469 | F48: =F43-SUM(F44:F47) -> 45.060349 | G48: =G43-SUM(G44:G47) -> 55.278153 | H48: =H43-SUM(H44:H47) -> 66.832966 | I48: =I43-SUM(I44:I47) -> 79.872576
C50: Capex as % of Revenue | D50: =$D$44/$D$28 -> 0.046153846 | E50: 0.046153846 | F50: 0.046153846 | G50: 0.046153846 | H50: 0.046153846 | I50: 0.046153846
C51: D&A as a % of Capex | D51: =D32/D44 -> 1 | E51: 1 | F51: 1 | G51: 1 | H51: 1 | I51: 1
C52: NWC as a % of Revenue | D52: =D53/D28 -> 0.077 | E52: 0.077 | F52: 0.077 | G52: 0.077 | H52: 0.077 | I52: 0.077
C53: NWC $ | D53: 50.05 | E53: =E52*E28 -> 54.054 | F53: =F52*F28 -> 58.37832 | G53: =G52*G28 -> 63.048586 | H53: =H52*H28 -> 68.092472 | I53: =I52*I28 -> 73.53987
C54: Income Tax Rate | D54: -- | E54: 0.25 | F54: 0.25 | G54: 0.25 | H54: 0.25 | I54: 0.25
D55: PF | E55: Projected
C56: Term Loan Pay Down | D56: 2014 | E56: =D56+1 -> 2015 | F56: =+E56+1 -> 2016 | G56: =+F56+1 -> 2017 | H56: =+G56+1 -> 2018 | I56: =+H56+1 -> 2019
C57: BOP | E57: =D59 -> 524.875 | F57: =E59 -> 488.82953 | G57: =F59 -> 443.76918 | H57: =G59 -> 388.49103 | I57: =H59 -> 321.65806
C58: Paydown | E58: =(IF(E48<0,0,-MIN(E57,E48))) -> -36.045469 | F58: =(IF(F48<0,0,-MIN(F57,F48))) -> -45.060349 | G58: =(IF(G48<0,0,-MIN(G57,G48))) -> -55.278153 | H58: =(IF(H48<0,0,-MIN(H57,H48))) -> -66.832966 | I58: =(IF(I48<0,0,-MIN(I57,I48))) -> -79.872576
C59: EOP | D59: =$D$20 -> 524.875 | E59: =E57+E58 -> 488.82953 | F59: =F57+F58 -> 443.76918 | G59: =G57+G58 -> 388.49103 | H59: =H57+H58 -> 321.65806 | I59: =I57+I58 -> 241.78549
C60: Gross Leverage | D60: =D59/D43 -> 4.25 | E60: =E59/E43 -> 3.570966 | F60: =F59/F43 -> 3.0016611 | G60: =G59/G43 -> 2.4331101 | H60: =H59/H43 -> 1.8653119 | I60: =I59/I43 -> 1.2982654
C62: Average Balance | E62: =AVERAGE(E57,E59) -> 506.85227 | F62: =AVERAGE(F57,F59) -> 466.29936 | G62: =AVERAGE(G57,G59) -> 416.13011 | H62: =AVERAGE(H57,H59) -> 355.07455 | I62: =AVERAGE(I57,I59) -> 281.72177
C63: All-In Interest Expense | E63: =E62*($K$21+$L$21) -> 51.090708 | F63: =F62*($K$21+$L$21) -> 47.002975 | G63: =G62*($K$21+$L$21) -> 41.945915 | H63: =H62*($K$21+$L$21) -> 35.791514 | I63: =I62*($K$21+$L$21) -> 28.397555
C66: Exit Assumptions and Calculations
C67: EV Multiple | D67: 7.6275304
C68: EBITDA | D68: =$I$43 -> 186.23733
C69: TEV | D69: =D67*D68 -> 1420.5309
C70: Existing Debt | D70: =I59 -> 241.78549
C71: Est. Txn Fees & Expenses | D71: =$E$71*$D$69 -> 42.615928 | E71: 0.03
C72: Consideration to Equity Holders @ Exit | D72: =D69-D70-D71 -> 1136.1295
C73: Sponsor Ownership % | D73: 0.9
C74: Sponsor Equity Proceeds @ Exit | D74: =D72*D73 -> 1022.5166
C75: Sponsor Equity Check @ Entry | D75: =$D$22 -> 576.592
C77: MOIC | D77: =D74/D75 -> 1.7733797
C78: IRR | D78: =D77^(1/5)-1 -> 0.12139947
C80: Quick IRR Calc Method
C81: =MOIC^(1 / Investment Period) -1
C84: Approach & Best Practices
C85: At this stage in a process you are far less concerned about validating the underlying operating assumptions and far more focused on making sure the "quick & dirty" returns remotely work. Less is more at this stage - you don't need to get super granular on the structure, fees etc. Keep it so simple that you could do this on a napkin. Best practices: format & hardcode the key cells that drive the analysis first. After you have the drivers in place, begin linking / calculating the rest. No need to have a bunch of complex calcs here, you want to be able to quickly toggle your assumptions with ease.
C86: Paper LBO Steps & Notes
C87: 1) Input the entry assumptions. Note - For simplicity, you don't have to account for the existing debt at this stage (cash free & debt free). However, if you have the info, its worth including.
C88: 2) Solve for Equity Purchase Price
C89: 3) Set up the S&U. Note - For a paper LBO, no need to get fancy on the cap structure and fees. Keep it simple and just assume a max leverage multiple and cost of debt (don't worry about OID or other fees on the debt). Make new sponsor equity the plug for the S&U.
C90: 4) Set up the "simple" P&L. Note - Set up the key P&L driver assumptions (revenue & margins) and leave interest expense blank at this stage
C91: 5) Set up the "simple" FCF build. Note - Continue to keep interest expense blank and input the key driver assumptions for FCF (Capex, D&A, NWC, Tax Rate)
C92: 6) Set up the debt paydown table and keep the assumptions super high level (don’t worry about the revolver funding losses, assume 100% of FCF is used to repay debt, don't need to account for the term loan amort at this stage).
C93: 7) Calculate interest expense and link the #"s back to the P&L and FCF build
... C108: Note: model requires iterative calculation; this file is saved with it enabled.

Sheet Scenario Summary
B2: Dynacast LBO - Scenario Summary ($ in millions)
B4: Metric | C4: Base | D4: Bull | E4: Bear
B5: Revenue growth (2015-19, each yr) | C5: ='Paper LBO - Template'!E29 -> 0.09 | D5: ='Bull Case'!E29 -> 0.119 | E5: ='Bear Case'!E29 -> 0.08
B6: EBITDA margin 2015 | C6: ='Paper LBO - Template'!E31 -> 0.2 | D6: ='Bull Case'!E31 -> 0.205 | E6: ='Bear Case'!E31 -> 0.195
B7: EBITDA margin 2016-19 | C7: ='Paper LBO - Template'!F31 -> 0.21 | D7: ='Bull Case'!F31 -> 0.215 | E7: ='Bear Case'!F31 -> 0.195
B8: Exit EV / EBITDA | C8: ='Paper LBO - Template'!D67 -> 8.9 | D8: ='Bull Case'!D67 -> 10.1 | E8: ='Bear Case'!D67 -> 7.6275304
B9: 2019 Revenue | C9: ='Paper LBO - Template'!I28 -> 1000.1056 | D9: ='Bull Case'!I28 -> 1140.4173 | E9: ='Bear Case'!I28 -> 955.06325
B10: 2019 EBITDA | C10: ='Paper LBO - Template'!I30 -> 210.02217 | D10: ='Bull Case'!I30 -> 245.18972 | E10: ='Bear Case'!I30 -> 186.23733
B11: Term loan balance, end 2019 | C11: ='Paper LBO - Template'!I59 -> 180.5762 | D11: ='Bull Case'!I59 -> 120.79323 | E11: ='Bear Case'!I59 -> 241.78549
B12: Gross leverage, end 2019 | C12: ='Paper LBO - Template'!I60 -> 0.85979589 | D12: ='Bull Case'!I60 -> 0.49265209 | E12: ='Bear Case'!I60 -> 1.2982654
B13: Exit TEV | C13: ='Paper LBO - Template'!D69 -> 1869.1973 | D13: ='Bull Case'!D69 -> 2476.4161 | E13: ='Bear Case'!D69 -> 1420.5309
B14: Equity to holders at exit | C14: ='Paper LBO - Template'!D72 -> 1632.5452 | D14: ='Bull Case'!D72 -> 2281.3304 | E14: ='Bear Case'!D72 -> 1136.1295
B15: Sponsor proceeds | C15: ='Paper LBO - Template'!D74 -> 1469.2907 | D15: ='Bull Case'!D74 -> 2053.1974 | E15: ='Bear Case'!D74 -> 1022.5166
B16: Sponsor equity at entry | C16: ='Paper LBO - Template'!D75 -> 576.592 | D16: ='Bull Case'!D75 -> 576.592 | E16: ='Bear Case'!D75 -> 576.592
B17: MOIC | C17: ='Paper LBO - Template'!D77 -> 2.5482328 | D17: ='Bull Case'!D77 -> 3.5609189 | E17: ='Bear Case'!D77 -> 1.7733797
B18: IRR | C18: ='Paper LBO - Template'!D78 -> 0.20572377 | D18: ='Bull Case'!D78 -> 0.28917661 | E18: ='Bear Case'!D78 -> 0.12139947
B20: Fund hurdle check
B21: Target / floor (user brief) | D21: 25-30% target | E21: 12-15% floor
B22: Result | D22: =IF(AND(D18>=0.25,D18<=0.3),"In 25-30% target band",IF(D18>0.3,"Above band","Below band")) -> In 25-30% target band | E22: =IF(AND(E18>=0.12,E18<=0.15),"In 12-15% band",IF(E18>0.15,"Above band","Below floor")) -> In 12-15% band
B24: All scenarios share entry (8.9x, 4.25x term loan, 3% fees, 5% rollover), tax 25%, capex 4.6% of revenue, NWC 7.7%, 10% exit dilution. Only the three yellow-shaded input groups differ on each scenario tab. Iterative calculation must be on.

Sheet Returns Attribution
B2: Dynacast LBO - Returns Attribution ($ in millions)
C3: Base | D3: Bull | E3: Bear
B5: ENTRY (close, early 2015)
B6: Entry EV / EBITDA | C6: ='Paper LBO - Template'!D6 -> 8.9 | D6: ='Bull Case'!D6 -> 8.9 | E6: ='Bear Case'!D6 -> 8.9
B7: Entry EBITDA (PF LTM) | C7: ='Paper LBO - Template'!D7 -> 123.5 | D7: ='Bull Case'!D7 -> 123.5 | E7: ='Bear Case'!D7 -> 123.5
B8: Entry TEV | C8: ='Paper LBO - Template'!D8 -> 1099.15 | D8: ='Bull Case'!D8 -> 1099.15 | E8: ='Bear Case'!D8 -> 1099.15
B9: Debt at entry (Term Loan B + revolver) | C9: ='Paper LBO - Template'!D20+'Paper LBO - Template'!D19 -> 524.875 | D9: ='Bull Case'!D20+'Bull Case'!D19 -> 524.875 | E9: ='Bear Case'!D20+'Bear Case'!D19 -> 524.875
B10: Entry transaction fees | C10: ='Paper LBO - Template'!I21 -> 32.9745 | D10: ='Bull Case'!I21 -> 32.9745 | E10: ='Bear Case'!I21 -> 32.9745
B11: Total equity invested (sponsor + mgmt rollover) | C11: ='Paper LBO - Template'!D21+'Paper LBO - Template'!D22 -> 607.2495 | D11: ='Bull Case'!D21+'Bull Case'!D22 -> 607.2495 | E11: ='Bear Case'!D21+'Bear Case'!D22 -> 607.2495
B12: of which sponsor equity | C12: ='Paper LBO - Template'!D22 -> 576.592 | D12: ='Bull Case'!D22 -> 576.592 | E12: ='Bear Case'!D22 -> 576.592
B13: Sponsor ownership at entry | C13: =C12/C11 -> 0.94951416 | D13: =D12/D11 -> 0.94951416 | E13: =E12/E11 -> 0.94951416
B14: EXIT (end 2019)
B15: Exit EV / EBITDA | C15: ='Paper LBO - Template'!D67 -> 8.9 | D15: ='Bull Case'!D67 -> 10.1 | E15: ='Bear Case'!D67 -> 7.6275304
B16: Exit EBITDA (2019) | C16: ='Paper LBO - Template'!D68 -> 210.02217 | D16: ='Bull Case'!D68 -> 245.18972 | E16: ='Bear Case'!D68 -> 186.23733
B17: Exit TEV | C17: ='Paper LBO - Template'!D69 -> 1869.1973 | D17: ='Bull Case'!D69 -> 2476.4161 | E17: ='Bear Case'!D69 -> 1420.5309
B18: Debt at exit (Term Loan B) | C18: ='Paper LBO - Template'!D70 -> 180.5762 | D18: ='Bull Case'!D70 -> 120.79323 | E18: ='Bear Case'!D70 -> 241.78549
B19: Exit transaction fees | C19: ='Paper LBO - Template'!D71 -> 56.075919 | D19: ='Bull Case'!D71 -> 74.292484 | E19: ='Bear Case'!D71 -> 42.615928
B20: Equity value to all holders at exit | C20: ='Paper LBO - Template'!D72 -> 1632.5452 | D20: ='Bull Case'!D72 -> 2281.3304 | E20: ='Bear Case'!D72 -> 1136.1295
B21: Sponsor ownership at exit (after mgmt incentive dilution) | C21: ='Paper LBO - Template'!D73 -> 0.9 | D21: ='Bull Case'!D73 -> 0.9 | E21: ='Bear Case'!D73 -> 0.9
B22: BRIDGE 1: CHANGE IN TOTAL EQUITY VALUE (100% of equity, not the sponsor)
B23: Total equity invested at entry | C23: =C11 -> 607.2495 | D23: =D11 -> 607.2495 | E23: =E11 -> 607.2495
B24: + EBITDA growth [(Exit EBITDA - Entry EBITDA) x Entry multiple] | C24: =(C16-C7)*C6 -> 770.04731 | D24: =(D16-D7)*D6 -> 1083.0385 | E24: =(E16-E7)*E6 -> 558.36227
B25: + Multiple expansion [(Exit multiple - Entry multiple) x Exit EBITDA] | C25: =(C15-C6)*C16 -> 0 | D25: =(D15-D6)*D16 -> 294.22766 | E25: =(E15-E6)*E16 -> -236.98135
B26: + Debt paydown [Entry debt - Exit debt] | C26: =C9-C18 -> 344.2988 | D26: =D9-D18 -> 404.08177 | E26: =E9-E18 -> 283.08951
B27: - Entry fees (funded with equity, not in entry TEV) | C27: =-C10 -> -32.9745 | D27: =-D10 -> -32.9745 | E27: =-E10 -> -32.9745
B28: - Exit fees | C28: =-C19 -> -56.075919 | D28: =-D19 -> -74.292484 | E28: =-E19 -> -42.615928
B29: = Equity value to all holders at exit | C29: =SUM(C23:C28) -> 1632.5452 | D29: =SUM(D23:D28) -> 2281.3304 | E29: =SUM(E23:E28) -> 1136.1295
B30: Check vs model exit equity (should be 0.0) | C30: =C29-C20 -> 0 | D30: =D29-D20 -> 0 | E30: =E29-E20 -> 0
B31: Total equity value created (100%) | C31: =C20-C11 -> 1025.2957 | D31: =D20-D11 -> 1674.0809 | E31: =E20-E11 -> 528.88
B32: Share of total equity value created
B33: EBITDA growth | C33: =C24/C31 -> 0.75104901 | D33: =D24/D31 -> 0.64694511 | E33: =E24/E31 -> 1.0557447
B34: Multiple expansion | C34: =C25/C31 -> 0 | D34: =D25/D31 -> 0.17575474 | E34: =E25/E31 -> -0.44808151
B35: Debt paydown | C35: =C26/C31 -> 0.3358044 | D35: =D26/D31 -> 0.24137529 | E35: =E26/E31 -> 0.53526227
B36: Fees | C36: =(C27+C28)/C31 -> -0.086853402 | D36: =(D27+D28)/D31 -> -0.064075149 | E36: =(E27+E28)/E31 -> -0.14292548
B37: BRIDGE 2: RECONCILE TO SPONSOR (ownership changes from the model)
B38: Sponsor share of EBITDA growth (at entry ownership) | C38: =C24*C13 -> 731.17083 | D38: =D24*D13 -> 1028.3604 | E38: =E24*E13 -> 530.17288
B39: Sponsor share of multiple expansion | C39: =C25*C13 -> 0 | D39: =D25*D13 -> 279.37333 | E39: =E25*E13 -> -225.01715
B40: Sponsor share of debt paydown | C40: =C26*C13 -> 326.91659 | D40: =D26*D13 -> 383.68137 | E40: =E26*E13 -> 268.7975
B41: Sponsor share of fees | C41: =(C27+C28)*C13 -> -84.554634 | D41: =(D27+D28)*D13 -> -101.85152 | E41: =(E27+E28)*E13 -> -71.774181
B42: - Dilution: (entry ownership - exit ownership) x exit equity value | C42: =-(C13-C21)*C20 -> -80.834107 | D42: =-(D13-D21)*D20 -> -112.95816 | E42: =-(E13-E21)*E20 -> -56.2545
B43: = Sponsor gain | C43: =SUM(C38:C42) -> 892.69867 | D43: =SUM(D38:D42) -> 1476.6054 | E43: =SUM(E38:E42) -> 445.92455
B44: Check vs model: sponsor proceeds - sponsor equity invested (should be 0.0) | C44: =C43-('Paper LBO - Template'!D74-'Paper LBO - Template'!D75) -> 0 | D44: =D43-('Bull Case'!D74-'Bull Case'!D75) -> 0 | E44: =E43-('Bear Case'!D74-'Bear Case'!D75) -> 0
B45: Sponsor proceeds at exit (model) | C45: ='Paper LBO - Template'!D74 -> 1469.2907 | D45: ='Bull Case'!D74 -> 2053.1974 | E45: ='Bear Case'!D74 -> 1022.5166
B46: SPONSOR RETURN ATTRIBUTION
B47: MOIC | C47: ='Paper LBO - Template'!D77 -> 2.5482328 | D47: ='Bull Case'!D77 -> 3.5609189 | E47: ='Bear Case'!D77 -> 1.7733797
B48: EBITDA growth (MOIC turns) | C48: =C38/C12 -> 1.2680905 | D48: =D38/D12 -> 1.7835148 | E48: =E38/E12 -> 0.919494
B49: Multiple expansion | C49: =C39/C12 -> 0 | D49: =D39/D12 -> 0.48452516 | E49: =E39/E12 -> -0.39025368
B50: Debt paydown | C50: =C40/C12 -> 0.56698079 | D50: =D40/D12 -> 0.66542957 | E50: =E40/E12 -> 0.4661832
B51: Fees | C51: =C41/C12 -> -0.14664552 | D51: =D41/D12 -> -0.176644 | E51: =E41/E12 -> -0.12448002
B52: Dilution | C52: =C42/C12 -> -0.1401929 | D52: =D42/D12 -> -0.19590657 | E52: =E42/E12 -> -0.097563789
B53: Return of capital (1.00x) | C53: =1 -> 1 | D53: =1 -> 1 | E53: =1 -> 1
B54: Check: sum of turns - MOIC (should be 0.00) | C54: =SUM(C48:C53)-C47 -> 0 | D54: =SUM(D48:D53)-D47 -> 0 | E54: =SUM(E48:E53)-E47 -> 0
B55: IRR | C55: ='Paper LBO - Template'!D78 -> 0.20572377 | D55: ='Bull Case'!D78 -> 0.28917661 | E55: ='Bear Case'!D78 -> 0.12139947
B56: EBITDA growth (IRR pts, pro rata to sponsor gain) | C56: =C55*C38/C43 -> 0.16849943 | D56: =D55*D38/D43 -> 0.20139285 | E56: =E55*E38/E43 -> 0.14433542
B57: Multiple expansion | C57: =C55*C39/C43 -> 0 | D57: =D55*D39/D43 -> 0.054712135 | E57: =E55*E39/E43 -> -0.061259159
B58: Debt paydown | C58: =C55*C40/C43 -> 0.075338425 | D58: =D55*D40/D43 -> 0.075139695 | E58: =E55*E40/E43 -> 0.073178017
B59: Fees | C59: =C55*C41/C43 -> -0.019485744 | D59: =D55*D41/D43 -> -0.019946479 | E59: =E55*E41/E43 -> -0.019539959
B60: Dilution | C60: =C55*C42/C43 -> -0.018628343 | D60: =D55*D42/D43 -> -0.02212159 | E60: =E55*E42/E43 -> -0.015314848
B61: Share of sponsor gain
B62: EBITDA growth | C62: =C38/C43 -> 0.8190567 | D62: =D38/D43 -> 0.69643547 | E62: =E38/E43 -> 1.1889296
B63: Multiple expansion | C63: =C39/C43 -> 0 | D63: =D39/D43 -> 0.18919972 | E63: =E39/E43 -> -0.50460812
B64: Debt paydown | C64: =C40/C43 -> 0.36621157 | D64: =D40/D43 -> 0.25984015 | E64: =E40/E43 -> 0.60278695
B65: Fees | C65: =C41/C43 -> -0.094718001 | D65: =D41/D43 -> -0.068976804 | E65: =E41/E43 -> -0.16095589
B66: Dilution | C66: =C42/C43 -> -0.090550271 | D66: =D42/D43 -> -0.076498545 | E66: =E42/E43 -> -0.12615251
B68: How to read this tab
B69: 1) Bridge 1 explains the change in the equity value of ALL holders (sponsor + management rollover + incentive pool), from total equity invested at entry to equity value at exit. EBITDA growth is valued at the entry multiple; multiple expansion is valued on exit EBITDA; debt paydown is the Term Loan B reduction (the model carries no cash balance).
B70: 2) Fees are the reconciling item: the model funds 3% entry fees with equity (they are in Uses, not in entry TEV) and charges 3% exit fees against exit equity (D71). Without them the three drivers do not tie to equity value.
B71: 3) Bridge 2 converts to the sponsor. Entry ownership = sponsor equity / (sponsor + rollover) = about 94.9%; the model sets exit ownership at 90% (D73), which is the management incentive dilution, taken as given. The dilution line = (entry % - exit %) x exit equity value.
B72: 4) MOIC turns = sponsor gain by driver / sponsor equity invested, plus 1.00x return of capital, which sums to the model MOIC. IRR points are allocated pro rata to each driver's share of sponsor gain (an attribution convention, not a separate IRR calculation).
B73: 5) All cells are live formulas off the three case tabs; the grey check rows should read 0.0 / 0.00.

Sheet Key Stats
A5: Dynacast International Inc. > Financials > Key Stats
A7: In Millions of the trading currency, except per share items. | B7: Currency: | C7: Trading Currency | E7: Conversion: | F7: Today's Spot Rate
B8: Order: | C8: Latest on Right | E8: Units: | F8: S&P Capital IQ (Default)
B9: Decimals: | C9: Capital IQ (Default) | E9: Dilution: | F9: Basic
A12: Key Financials¹
A13: For the Fiscal Period Ending | B13: 12 months Dec-31-2008A | C13: 12 months Dec-31-2009A | D13: 12 months Dec-31-2010A | E13: 12 months Dec-31-2011A | F13: 12 months Dec-31-2012A | G13: 12 months Dec-31-2013A | H13: LTM² 12 months Sep-30-2014A | I13: 3Yr CAGR | J13: 5YR CAGR
A14: Year | B14: 0 | C14: =B14+1 -> 1 | D14: =C14+1 -> 2 | E14: =D14+1 -> 3 | F14: =E14+1 -> 4 | G14: =F14+1 -> 5 | H14: =G14+1 -> 6
A15: Currency | B15: USD | C15: USD | D15: USD | E15: USD | F15: USD | G15: USD | H15: USD
A17: Total Revenue | B17: 457.5 | C17: 327.8 | D17: 428.4 | E17: 478.7 | F17: 519.4 | G17: 580 | H17: 616.7 | I17: =((H17/E17)^(1/($H$14-E$14)))-1 -> 0.088103416 | J17: =((H17/C17)^(1/($H$14-C$14)))-1 -> 0.13473121
A18: Growth Over Prior Year | B18: NA | C18: -0.283498 | D18: 0.306894 | E18: 0.117413 | F18: 0.085021 | G18: 0.116673 | H18: 0.080602
A20: Gross Profit | B20: 95.4 | C20: 68.7 | D20: 102.2 | E20: 110.1 | F20: 121.4 | G20: 138.3 | H20: 145 | I20: =((H20/E20)^(1/($H$14-E$14)))-1 -> 0.096125365 | J20: =((H20/C20)^(1/($H$14-C$14)))-1 -> 0.16113376
A21: Margin % | B21: 0.208524 | C21: 0.209579 | D21: 0.238562 | E21: 0.229997 | F21: 0.233731 | G21: 0.238448 | H21: 0.235122
A23: EBITDA | B23: 66.4 | C23: 49.2 | D23: 78.3 | E23: 86.5 | F23: 91.7 | G23: 103.9 | H23: 113 | I23: =((H23/E23)^(1/($H$14-E$14)))-1 -> 0.093169347
A24: Margin % | B24: 0.145136 | C24: 0.150091 | D24: 0.182773 | E24: 0.180697 | F24: 0.176549 | G24: 0.179137 | H24: 0.183233
A26: EBIT | B26: 48.2 | C26: 31.1 | D26: 62.4 | E26: 64.4 | F26: 59.3 | G26: 69.4 | H26: 74.8 | I26: =((H26/E26)^(1/($H$14-E$14)))-1 -> 0.051167464 | J26: =((H26/C26)^(1/($H$14-C$14)))-1 -> 0.19186823
A27: Margin % | B27: 0.105355 | C27: 0.094874 | D27: 0.145658 | E27: 0.134531 | F27: 0.11417 | G27: 0.119655 | H27: 0.12129
A29: Earnings from Cont. Ops. | B29: 26.2 | C29: 14.5 | D29: 43.5 | E29: 7.4 | F29: -0.6 | G29: 1.2 | H29: 11 | I29: =((H29/E29)^(1/($H$14-E$14)))-1 -> 0.14126629 | J29: =((H29/C29)^(1/($H$14-C$14)))-1 -> -0.053752083
A30: Margin % | B30: 0.057267 | C30: 0.044234 | D30: 0.10154 | E30: 0.015458 | F30: -0.001155 | G30: 0.002068 | H30: 0.017836
A32: Net Income | B32: 25.8 | C32: 14.2 | D32: 43.1 | E32: 7.1 | F32: -0.9 | G32: 0.8 | H32: 10.5 | I32: =((H32/E32)^(1/($H$14-E$14)))-1 -> 0.13931457 | J32: =((H32/C32)^(1/($H$14-C$14)))-1 -> -0.058587001
A33: Margin % | B33: 0.056393 | C33: 0.043319 | D33: 0.100606 | E33: 0.014831 | F33: -0.001732 | G33: 0.001379 | H33: 0.017026
A35: Diluted EPS Excl. Extra Items³ | B35: NA | C35: NA | D35: NA | E35: -144.12 | F35: -6.47 | G35: 4.705882 | H35: 61.764705
A36: Growth Over Prior Year | B36: NA | C36: NA | D36: NA | E36: NA | F36: NM | G36: NM | H36: 2
A41: ¹All results are taken from the most recently filed statement for each period. When there has been more than one, earlier filings can be viewed on the individual statement pages.
A42: ²Growth rates for the LTM period are calculated against the LTM period ending 12 months before.
A45: Latest Capitalization (Millions of USD)
A46: Currency | B46: USD
A47: Share Price | B47: -
A48: Shares Out. | B48: -
A50: Market Capitalization | B50: -
A51: - Cash & Short Term Investments | B51: 40.3
A52: + Total Debt | B52: 486 | C52: =B52/H23 -> 4.300885
A53: + Pref. Equity | B53: -
A54: + Total Minority Interest | B54: 4.2
A55: - Long Term Marketable Securities | B55: -
A56: = Total Enterprise Value (TEV) | B56: -
A58: Book Value of Common Equity | B58: 120.7
A59: + Pref. Equity | B59: -
A60: + Total Minority Interest | B60: 4.2
A61: + Total Debt | B61: 486
A62: = Total Capital | B62: 610.9
A64: **For companies that have multiple share classes that publicly trade, we are incorporating the different prices to calculate our company level market capitalization. Please click on the value to see the detailed calculation. Prices shown on this page are the close price of the company’s primary stock class. Shares shown on this page are total company as-reported share values.
A68: Total Liability includes Total Debt, Minority Interest and Pref. Equity.
A69: Net Liability includes Total Liability, net of Cash and Short Term Investments.
A70: TEV includes Market Cap and Net Liability.
A71: Total Capital includes Common Equity and Total Liability.
A73: Valuation Multiples based on Current Capitalization
A74: For the Fiscal Period Ending | B74: 12 months Dec-31-2010A | C74: 12 months Dec-31-2011A | D74: 12 months Dec-31-2012A | E74: 12 months Dec-31-2013A | F74: LTM 12 months Sep-30-2014A
A75: TEV/Total Revenue | B75: - | C75: - | D75: - | E75: - | F75: -
A77: TEV/EBITDA | B77: - | C77: - | D77: - | E77: - | F77: -
A79: TEV/EBIT | B79: - | C79: - | D79: - | E79: - | F79: -
A81: P/Diluted EPS Before Extra | B81: - | C81: - | D81: - | E81: - | F81: -
A83: P/BV | B83: - | C83: - | D83: - | E83: - | F83: -
A85: Price/Tang BV | B85: - | C85: - | D85: - | E85: - | F85: -

Sheet Income Statement
A5: Dynacast International Inc. > Financials > Income Statement
A7: In Millions of the reported currency, except per share items. | B7: Template: | C7: Standard | E7: Restatement: | F7: Latest Filings
B8: Period Type: | C8: Annual | E8: Order: | F8: Latest on Right
B9: Currency: | C9: Reported Currency | E9: Conversion: | F9: Today's Spot Rate
B10: Units: | C10: S&P Capital IQ (Default) | E10: Decimals: | F10: Capital IQ (Default)
B11: Source: | C11: Capital IQ & Proprietary Data
A14: Income Statement
A15: For the Fiscal Period Ending | B15: 12 months Dec-31-2009 | C15: Reclassified 12 months Dec-31-2010 | D15: Restated 12 months Dec-31-2011 | E15: Reclassified 12 months Dec-31-2012 | F15: 12 months Dec-31-2013 | G15: LTM 12 months Sep-30-2014
A16: Currency | B16: USD | C16: USD | D16: USD | E16: USD | F16: USD | G16: USD
A18: Revenue | B18: 327.8 | C18: 428.4 | D18: 478.7 | E18: 519.4 | F18: 580 | G18: 616.7
A19: Other Revenue | B19: - | C19: - | D19: - | E19: - | F19: - | G19: -
A20: Total Revenue | B20: 327.8 | C20: 428.4 | D20: 478.7 | E20: 519.4 | F20: 580 | G20: 616.7
A22: Cost Of Goods Sold | B22: 259.1 | C22: 326.2 | D22: 368.6 | E22: 398 | F22: 441.7 | G22: 471.7
A23: Gross Profit | B23: 68.7 | C23: 102.2 | D23: 110.1 | E23: 121.4 | F23: 138.3 | G23: 145
A25: Selling General & Admin Exp. | B25: 37.6 | C25: 39.8 | D25: 45.7 | E25: 62.1 | F25: 68.9 | G25: 70.2
A26: R & D Exp. | B26: - | C26: - | D26: - | E26: - | F26: - | G26: -
A27: Depreciation & Amort. | B27: - | C27: - | D27: - | E27: - | F27: - | G27: -
A28: Other Operating Expense/(Income) | B28: - | C28: - | D28: - | E28: - | F28: - | G28: -
A30: Other Operating Exp., Total | B30: 37.6 | C30: 39.8 | D30: 45.7 | E30: 62.1 | F30: 68.9 | G30: 70.2
A32: Operating Income | B32: 31.1 | C32: 62.4 | D32: 64.4 | E32: 59.3 | F32: 69.4 | G32: 74.8
A34: Interest Expense | B34: -8.1 | C34: -4.9 | D34: -27.7 | E34: -48.7 | F34: -47.9 | G34: -46
A35: Interest and Invest. Income | B35: - | C35: 1.2 | D35: - | E35: - | F35: - | G35: -
A36: Net Interest Exp. | B36: -8.1 | C36: -3.7 | D36: -27.7 | E36: -48.7 | F36: -47.9 | G36: -46
A40: Currency Exchange Gains (Loss) | B40: - | C40: - | D40: - | E40: - | F40: - | G40: 1.5
A41: Other Non-Operating Inc. (Exp.) | B41: 2.5 | C41: - | D41: 0.7 | E41: -3.2 | F41: -5.7 | G41: -7.4
A42: EBT Excl. Unusual Items | B42: 25.5 | C42: 58.7 | D42: 37.4 | E42: 7.4 | F42: 15.8 | G42: 22.9
A44: Restructuring Charges | B44: -2.9 | C44: -10.9 | D44: 0.7 | E44: -0.5 | F44: - | G44: -
A45: Merger & Related Restruct. Charges | B45: - | C45: - | D45: -23 | E45: -0.6 | F45: - | G45: -1.4
A46: Impairment of Goodwill | B46: - | C46: - | D46: - | E46: - | F46: - | G46: -
A47: Insurance Settlements | B47: - | C47: - | D47: - | E47: - | F47: - | G47: 2.3
A48: Other Unusual Items | B48: - | C48: -0.7 | D48: - | E48: - | F48: - | G48: -0.4
A49: EBT Incl. Unusual Items | B49: 22.6 | C49: 47.1 | D49: 15.1 | E49: 6.3 | F49: 15.8 | G49: 23.4
A51: Income Tax Expense | B51: 8.1 | C51: 3.6 | D51: 7.7 | E51: 6.9 | F51: 14.6 | G51: 12.4
A52: Earnings from Cont. Ops. | B52: 14.5 | C52: 43.5 | D52: 7.4 | E52: -0.6 | F52: 1.2 | G52: 11
A54: Earnings of Discontinued Ops. | B54: - | C54: - | D54: - | E54: - | F54: - | G54: -
A55: Extraord. Item & Account. Change | B55: - | C55: - | D55: - | E55: - | F55: - | G55: -
A56: Net Income to Company | B56: 14.5 | C56: 43.5 | D56: 7.4 | E56: -0.6 | F56: 1.2 | G56: 11
A58: Minority Int. in Earnings | B58: -0.3 | C58: -0.4 | D58: -0.3 | E58: -0.3 | F58: -0.4 | G58: -0.5
A59: Net Income | B59: 14.2 | C59: 43.1 | D59: 7.1 | E59: -0.9 | F59: 0.8 | G59: 10.5
A61: Pref. Dividends and Other Adj. | B61: - | C61: - | D61: 31.6 | E61: 0.2 | F61: - | G61: -
A63: NI to Common Incl Extra Items | B63: 14.2 | C63: 43.1 | D63: -24.5 | E63: -1.1 | F63: 0.8 | G63: 10.5
A64: NI to Common Excl. Extra Items | B64: 14.2 | C64: 43.1 | D64: -24.5 | E64: -1.1 | F64: 0.8 | G64: 10.5
A66: Per Share Items
A67: Basic EPS | B67: NA | C67: NA | D67: -144.12 | E67: -6.47 | F67: 4.71 | G67: 61.76
A68: Basic EPS Excl. Extra Items | B68: NA | C68: NA | D68: -144.12 | E68: -6.47 | F68: 4.705882 | G68: 61.764705
A69: Weighted Avg. Basic Shares Out. | B69: NA | C69: NA | D69: 0.17 | E69: 0.17 | F69: 0.17 | G69: 0.17
A71: Diluted EPS | B71: NA | C71: NA | D71: -144.12 | E71: -6.47 | F71: 4.71 | G71: 61.76
A72: Diluted EPS Excl. Extra Items | B72: NA | C72: NA | D72: -144.12 | E72: -6.47 | F72: 4.705882 | G72: 61.764705
A73: Weighted Avg. Diluted Shares Out. | B73: NA | C73: NA | D73: 0.17 | E73: 0.17 | F73: 0.17 | G73: 0.17
A75: Normalized Basic EPS | B75: NA | C75: NA | D75: 135.74 | E75: 25.44 | F75: 55.74 | G75: 81.25
A76: Normalized Diluted EPS | B76: NA | C76: NA | D76: 135.73529 | E76: 25.441176 | F76: 55.735294 | G76: 81.25
A78: Dividends per Share | B78: NA | C78: NA | D78: NA | E78: NA | F78: NA | G78: NA
A79: Payout Ratio % | B79: NA | C79: 0.25522 | D79: 1.816901 | E79: NA | F79: 2.25 | G79: 0.67619
A81: Supplemental Items
A82: EBITDA | B82: 49.2 | C82: 78.3 | D82: 86.5 | E82: 91.7 | F82: 103.9 | G82: 113
A83: EBITA | B83: 35.5 | C83: 66.6 | D83: 73.7 | E83: 75.2 | F83: 85.2 | G83: 90.4
A84: EBIT | B84: 31.1 | C84: 62.4 | D84: 64.4 | E84: 59.3 | F84: 69.4 | G84: 74.8
A85: EBITDAR | B85: 53.4 | C85: 82.9 | D85: 92.3 | E85: 98.4 | F85: 112.1 | G85: NA
A86: Effective Tax Rate % | B86: 0.358407 | C86: 0.076433 | D86: 0.509933 | E86: 1.095238 | F86: 0.92405 | G86: 0.529914
A87: Current Domestic Taxes | B87: 1 | C87: 0.4 | D87: 1.1 | E87: 0.4 | F87: 1.2 | G87: 1.2
A88: Current Foreign Taxes | B88: 6 | C88: 2.6 | D88: 13.1 | E88: 11.1 | F88: 15.6 | G88: 15.6
A89: Total Current Taxes | B89: 7 | C89: 3 | D89: 14.2 | E89: 11.5 | F89: 16.8 | G89: 16.8
A90: Deferred Domestic Taxes | B90: -2.8 | C90: -3.4 | D90: -4.9 | E90: -0.7 | F90: 0.1 | G90: 0.1
A91: Deferred Foreign Taxes | B91: 3.9 | C91: 4 | D91: -1.6 | E91: -3.9 | F91: -2.3 | G91: -2.3
A92: Total Deferred Taxes | B92: 1.1 | C92: 0.6 | D92: -6.5 | E92: -4.6 | F92: -2.2 | G92: -2.2
A94: Normalized Net Income | B94: 15.6375 | C94: 36.2875 | D94: 23.075 | E94: 4.325 | F94: 9.475 | G94: 13.8125
A95: Interest on Long Term Debt | B95: 7.9 | C95: NA | D95: NA | E95: 35.9 | F95: 35.2 | G95: NA
A96: Non-Cash Pension Expense | B96: 1.2 | C96: 1 | D96: 0.5 | E96: 0.9 | F96: 0.6 | G96: -
A97: Filing Date | B97: 41088 | C97: 41348 | D97: 41712 | E97: 41712 | F97: 41712 | G97: 41957
A98: Restatement Type | B98: NCA | C98: RC | D98: RS | E98: RC | F98: O | G98: O
A99: Calculation Type | B99: REP | C99: REP | D99: REP | E99: REP | F99: REP | G99: LTM
A101: Supplemental Operating Expense Items
A102: General and Administrative Exp. | B102: NA | C102: NA | D102: NA | E102: NA | F102: NA | G102: -1.3
A103: R&D Exp. | B103: NA | C103: NA | D103: NA | E103: 3.5 | F103: 3.6 | G103: 6.3
A104: Net Rental Exp. | B104: 4.2 | C104: 4.6 | D104: 5.8 | E104: 6.7 | F104: 8.2 | G104: NA
A105: Imputed Oper. Lease Interest Exp. | B105: - | C105: 1.686802 | D105: 5.183622 | E105: 6.004165 | F105: 7.070696 | G105: -
A106: Imputed Oper. Lease Depreciation | B106: - | C106: 2.913198 | D106: 0.616378 | E106: 0.695835 | F106: 1.129304 | G106: -
A109: Note: For multiple class companies, per share items are primary class equivalent, and for foreign companies listed as primary ADRs, per share items are ADR-equivalent.

Sheet Balance Sheet
A5: Dynacast International Inc. > Financials > Balance Sheet
A7: In Millions of the reported currency, except per share items. | B7: Template: | C7: Standard | E7: Restatement: | F7: Latest Filings
B8: Period Type: | C8: Annual | E8: Order: | F8: Latest on Right
B9: Currency: | C9: Reported Currency | E9: Conversion: | F9: Today's Spot Rate
B10: Units: | C10: S&P Capital IQ (Default) | E10: Decimals: | F10: Capital IQ (Default)
B11: Source: | C11: Capital IQ & Proprietary Data
A14: Balance Sheet
A15: Balance Sheet as of: | B15: 40178 | C15: 40543 | D15: 40908 | E15: Restated Dec-31-2012 | F15: 41639 | G15: 41912
A16: Currency | B16: USD | C16: USD | D16: USD | E16: USD | F16: USD | G16: USD
A17: ASSETS
A18: Cash And Equivalents | B18: 57.3 | C18: 27.8 | D18: 21.1 | E18: 28 | F18: 36.8 | G18: 40.3
A19: Total Cash & ST Investments | B19: 57.3 | C19: 27.8 | D19: 21.1 | E19: 28 | F19: 36.8 | G19: 40.3
I20: NWC Build | J20: FYE Dec 2013 | K20: LTM Sep 2014
A21: Accounts Receivable | B21: 51.8 | C21: 60.4 | D21: 66.9 | E21: 87.6 | F21: 97 | G21: 108 | I21: CA | J21: =F21+SUM(F25:F28) -> 162.1 | K21: =G21+SUM(G25:G28) -> 181.6
A22: Other Receivables | B22: 4.1 | C22: 0.2 | D22: - | E22: - | F22: - | G22: - | I22: CL | J22: =F50-F45 -> 155.3 | K22: =G50-G45 -> 146.4
A23: Total Receivables | B23: 55.9 | C23: 60.6 | D23: 66.9 | E23: 87.6 | F23: 97 | G23: 108 | I23: NWC | J23: =J21-J22 -> 6.8 | K23: =K21-K22 -> 35.2
I24: Net Change | K24: =J23-K23 -> -28.4
A25: Inventory | B25: 30.1 | C25: 36.2 | D25: 39 | E25: 36.7 | F25: 45 | G25: 49.7
A26: Prepaid Exp. | B26: 1.9 | C26: 2 | D26: 8.2 | E26: 14.2 | F26: 15.2 | G26: 17.4
A27: Deferred Tax Assets, Curr. | B27: 1.9 | C27: 5.5 | D27: 5.8 | E27: 4.3 | F27: 4.9 | G27: 5.9
A28: Other Current Assets | B28: 0.6 | C28: 4.3 | D28: 1.3 | E28: 0.3 | F28: - | G28: 0.6
A29: Total Current Assets | B29: 147.7 | C29: 136.4 | D29: 142.3 | E29: 171.1 | F29: 198.9 | G29: 221.9
A31: Gross Property, Plant & Equipment | B31: 233.5 | C31: 219 | D31: 126.4 | E31: 151.2 | F31: 190.4 | G31: -
A32: Accumulated Depreciation | B32: -168.3 | C32: -155.5 | D32: -6.5 | E32: -23.7 | F32: -41.7 | G32: -
A33: Net Property, Plant & Equipment | B33: 65.2 | C33: 63.5 | D33: 119.9 | E33: 127.5 | F33: 148.7 | G33: 153.3
A35: Goodwill | B35: 326.9 | C35: 320.8 | D35: 238.4 | E35: 242.8 | F35: 246.7 | G35: 264.4
A36: Other Intangibles | B36: 37.8 | C36: 32.6 | D36: 270.7 | E36: 261.9 | F36: 249 | G36: 240.8
A37: Deferred Tax Assets, LT | B37: 0.1 | C37: 2 | D37: 4.9 | E37: 5.3 | F37: 5.1 | G37: 4.3
A38: Deferred Charges, LT | B38: - | C38: - | D38: 22.1 | E38: 19.7 | F38: 15.7 | G38: 13.4
A39: Other Long-Term Assets | B39: - | C39: - | D39: 2.2 | E39: 4.5 | F39: 4.6 | G39: 4.3
A40: Total Assets | B40: 577.7 | C40: 555.3 | D40: 800.5 | E40: 832.8 | F40: 868.7 | G40: 902.4
A42: LIABILITIES
A43: Accounts Payable | B43: 47.4 | C43: 48.6 | D43: 52.7 | E43: 62.1 | F43: 67.7 | G43: 65.6
A44: Accrued Exp. | B44: 23.9 | C44: 30.5 | D44: 58.1 | E44: 64 | F44: 60.2 | G44: 57.3
A45: Curr. Port. of LT Debt | B45: 0.9 | C45: 0.4 | D45: 5 | E45: 6.3 | F45: 5.6 | G45: 19.5
A46: Curr. Income Taxes Payable | B46: 6.5 | C46: 2.7 | D46: 6.8 | E46: 3 | F46: 5.8 | G46: 6.2
A47: Unearned Revenue, Current | B47: 8.7 | C47: 8.2 | D47: 8.4 | E47: 8.4 | F47: 17.5 | G47: 16.2
A48: Def. Tax Liability, Curr. | B48: 0.9 | C48: 1.1 | D48: 1.3 | E48: 0.2 | F48: 0.4 | G48: 0.6
A49: Other Current Liabilities | B49: 4.8 | C49: 10.8 | D49: 0.2 | E49: 1.4 | F49: 3.7 | G49: 0.5
A50: Total Current Liabilities | B50: 93.1 | C50: 102.3 | D50: 132.5 | E50: 145.4 | F50: 160.9 | G50: 165.9
A52: Long-Term Debt | B52: 141 | C52: 71.5 | D52: 419 | E52: 439.2 | F52: 437.7 | G52: 466.5
A53: Pension & Other Post-Retire. Benefits | B53: 16.7 | C53: 17.1 | D53: 19.5 | E53: 23.5 | F53: 22.5 | G53: 21.1
A54: Def. Tax Liability, Non-Curr. | B54: 8.3 | C54: 8.9 | D54: 72.2 | E54: 70.3 | F54: 68.9 | G54: 67.9
A55: Other Non-Current Liabilities | B55: 0.8 | C55: 1.9 | D55: 12.6 | E55: 27.2 | F55: 44.7 | G55: 56.1
A56: Total Liabilities | B56: 259.9 | C56: 201.7 | D56: 655.8 | E56: 705.6 | F56: 734.7 | G56: 777.5
A58: Pref. Stock, Convertible | B58: - | C58: - | D58: 26.5 | E58: - | F58: - | G58: -
A59: Total Pref. Equity | B59: - | C59: - | D59: 26.5 | E59: - | F59: - | G59: -
A61: Common Stock | B61: 395.6 | C61: 399.2 | D61: 0.2 | E61: 0.2 | F61: 0.2 | G61: 0.2
A62: Additional Paid In Capital | B62: - | C62: - | D62: 166.6 | E62: 167.5 | F62: 167.5 | G62: 167.5
A63: Retained Earnings | B63: -70.2 | C63: -38.1 | D63: -23.6 | E63: -25.6 | F63: -24.8 | G63: -12.3
A64: Treasury Stock | B64: - | C64: - | D64: - | E64: - | F64: - | G64: -
A65: Comprehensive Inc. and Other | B65: -9.6 | C65: -9.7 | D65: -28.8 | E65: -18.7 | F65: -13 | G65: -34.7
A66: Total Common Equity | B66: 315.8 | C66: 351.4 | D66: 114.4 | E66: 123.4 | F66: 129.9 | G66: 120.7
A68: Minority Interest | B68: 2 | C68: 2.2 | D68: 3.8 | E68: 3.8 | F68: 4.1 | G68: 4.2
A70: Total Equity | B70: 317.8 | C70: 353.6 | D70: 144.7 | E70: 127.2 | F70: 134 | G70: 124.9
A72: Total Liabilities And Equity | B72: 577.7 | C72: 555.3 | D72: 800.5 | E72: 832.8 | F72: 868.7 | G72: 902.4
A74: Supplemental Items
A75: Total Shares Out. on Filing Date | B75: NA | C75: NA | D75: 0.17 | E75: 0.17 | F75: 0.17 | G75: 0.17
A76: Total Shares Out. on Balance Sheet Date | B76: NA | C76: NA | D76: 0.17 | E76: 0.17 | F76: 0.17 | G76: 0.17
A77: Book Value/Share | B77: NA | C77: NA | D77: 672.94 | E77: 725.88 | F77: 764.12 | G77: 710
A78: Tangible Book Value | B78: -48.9 | C78: -2 | D78: -394.7 | E78: -381.3 | F78: -365.8 | G78: -384.5
A79: Tangible Book Value/Share | B79: NA | C79: NA | D79: -2321.76 | E79: -2242.94 | F79: -2151.76 | G79: -2261.76
A80: Total Debt | B80: 141.9 | C80: 71.9 | D80: 424 | E80: 445.5 | F80: 443.3 | G80: 486
A81: Net Debt | B81: 84.6 | C81: 44.1 | D81: 402.9 | E81: 417.5 | F81: 406.5 | G81: 445.7
A82: Debt Equiv. of Unfunded Proj. Benefit Obligation | B82: 18.6 | C82: 19 | D82: 20.1 | E82: 24.1 | F82: 23.3 | G82: NA
A83: Debt Equivalent Oper. Leases | B83: 33.6 | C83: 36.8 | D83: 46.4 | E83: 53.6 | F83: 65.6 | G83: NA
A84: Total Minority Interest | B84: 2 | C84: 2.2 | D84: 3.8 | E84: 3.8 | F84: 4.1 | G84: 4.2
A85: Inventory Method | B85: NA | C85: Avg Cost | D85: LIFO | E85: LIFO | F85: Avg Cost | G85: NA
A86: LIFO Reserve | B86: NA | C86: NA | D86: 0.9 | E86: NA | F86: NA | G86: NA
A87: Raw Materials Inventory | B87: 9.3 | C87: 10.5 | D87: 6.4 | E87: 7.7 | F87: 8.7 | G87: 11.6
A88: Work in Progress Inventory | B88: 9.3 | C88: 11.4 | D88: 17.4 | E88: 12.6 | F88: 15.5 | G88: 19.1
A89: Finished Goods Inventory | B89: 11.5 | C89: 14.3 | D89: 14.3 | E89: 16.4 | F89: 20.8 | G89: 19
A90: Land | B90: 24.3 | C90: 24.7 | D90: 18.4 | E90: 19.6 | F90: 20.5 | G90: NA
A91: Machinery | B91: 209.2 | C91: 194.3 | D91: 108 | E91: 126.2 | F91: 160.2 | G91: NA
A92: Construction in Progress | B92: - | C92: - | D92: - | E92: 5.4 | F92: 9.7 | G92: -
A93: Full Time Employees | B93: NA | C93: 3000 | D93: 3000 | E93: 4683 | F93: 5510 | G93: NA
A94: Accum. Allowance for Doubtful Accts | B94: 3.4 | C94: 3 | D94: 2.5 | E94: 1.3 | F94: 1.5 | G94: NA
A95: Filing Date | B95: 41088 | C95: 41348 | D95: 41712 | E95: 41712 | F95: 41712 | G95: 41957
A96: Restatement Type | B96: NCA | C96: NC | D96: NC | E96: RS | F96: O | G96: O
A97: Calculation Type | B97: RUP | C97: RUP | D97: RUP | E97: REP | F97: REP | G97: REP
A100: Note: For multiple class companies, total share counts are primary class equivalent, and for foreign companies listed as primary ADRs, total share counts are ADR-equivalent.

Sheet Cash Flow
A5: Dynacast International Inc. > Financials > Cash Flow
A7: In Millions of the reported currency, except per share items. | B7: Template: | C7: Standard | E7: Restatement: | F7: Latest Filings
B8: Period Type: | C8: Annual | E8: Order: | F8: Latest on Right
B9: Currency: | C9: Reported Currency | E9: Conversion: | F9: Today's Spot Rate
B10: Units: | C10: S&P Capital IQ (Default) | E10: Decimals: | F10: Capital IQ (Default)
B11: Source: | C11: Capital IQ & Proprietary Data
A14: Cash Flow
A15: For the Fiscal Period Ending | B15: 12 months Dec-31-2009 | C15: 12 months Dec-31-2010 | D15: Restated 12 months Dec-31-2011 | E15: 12 months Dec-31-2012 | F15: 12 months Dec-31-2013 | G15: LTM 12 months Sep-30-2014
A16: Currency | B16: USD | C16: USD | D16: USD | E16: USD | F16: USD | G16: USD
A18: Net Income | B18: 14.2 | C18: 43.1 | D18: 7.4 | E18: -0.9 | F18: 0.8 | G18: 10.5
A19: Depreciation & Amort. | B19: 13.7 | C19: 11.7 | D19: 12.8 | E19: 16.5 | F19: 18.7 | G19: 22.6
A20: Amort. of Goodwill and Intangibles | B20: 4.4 | C20: 4.2 | D20: 9.3 | E20: 15.9 | F20: 15.8 | G20: 15.6
A21: Depreciation & Amort., Total | B21: 18.1 | C21: 15.9 | D21: 22.1 | E21: 32.4 | F21: 34.5 | G21: 38.2
A23: Other Amortization | B23: - | C23: - | D23: 7.1 | E23: 3.8 | F23: 4.8 | G23: 4.3
A24: Other Operating Activities | B24: 2.8 | C24: 1.7 | D24: 20.6 | E24: 8.8 | F24: 14.1 | G24: 7.2
A25: Change in Acc. Receivable | B25: 9.5 | C25: -8.8 | D25: -5.9 | E25: -20 | F25: -8.7 | G25: -7.1
A26: Change In Inventories | B26: 3.2 | C26: -6 | D26: -3.4 | E26: -3.4 | F26: -8 | G26: -7.5
A27: Change in Acc. Payable | B27: -1.2 | C27: 14.6 | D27: 10 | E27: 14 | F27: 5.1 | G27: 12.2
A28: Change in Inc. Taxes | B28: -2.1 | C28: -4.1 | D28: -2.7 | E28: 0.4 | F28: 4.7 | G28: 6.5
A29: Change in Other Net Operating Assets | B29: 3.2 | C29: 5.2 | D29: 0.1 | E29: -2.7 | F29: 6 | G29: -6.2
A30: Cash from Ops. | B30: 47.7 | C30: 61.6 | D30: 55.3 | E30: 32.4 | F30: 53.3 | G30: 58.1
A32: Capital Expenditure | B32: -6.9 | C32: -9.5 | D32: -14.3 | E32: -22 | F32: -39.7 | G32: -35.8
A33: Cash Acquisitions | B33: - | C33: - | D33: -586.4 | E33: - | F33: - | G33: -45.1
A34: Divestitures | B34: - | C34: - | D34: - | E34: - | F34: - | G34: -
A35: Invest. in Marketable & Equity Securt. | B35: - | C35: - | D35: - | E35: - | F35: - | G35: -
A36: Net (Inc.) Dec. in Loans Originated/Sold | B36: - | C36: - | D36: - | E36: - | F36: - | G36: -
A37: Other Investing Activities | B37: -27.2 | C37: -14.6 | D37: 27 | E37: 1.6 | F37: 0.1 | G37: -0.4
A38: Cash from Investing | B38: -34.1 | C38: -24.1 | D38: -573.7 | E38: -20.4 | F38: -39.6 | G38: -81.3
A40: Short Term Debt Issued | B40: - | C40: - | D40: 6.5 | E40: 24.5 | F40: 13.9 | G40: -
A41: Long-Term Debt Issued | B41: - | C41: - | D41: 400 | E41: - | F41: 5.8 | G41: -
A42: Total Debt Issued | B42: - | C42: - | D42: 406.5 | E42: 24.5 | F42: 19.7 | G42: 52.3
A43: Short Term Debt Repaid | B43: - | C43: - | D43: -34.1 | E43: -24.5 | F43: -13.9 | G43: -
A44: Long-Term Debt Repaid | B44: -1.3 | C44: -0.9 | D44: -2.9 | E44: -5 | F44: -8.1 | G44: -
A45: Total Debt Repaid | B45: -1.3 | C45: -0.9 | D45: -37 | E45: -29.5 | F45: -22 | G45: -9.2
A47: Issuance of Common Stock | B47: - | C47: - | D47: 174.3 | E47: - | F47: - | G47: -
A48: Issuance of Pref. Stock | B48: - | C48: - | D48: 53 | E48: - | F48: - | G48: -
A50: Pref. Dividends Paid | B50: - | C50: - | D50: - | E50: - | F50: -1.8 | G50: -7.1
A51: Common and/or Pref. Dividends Paid | B51: - | C51: -11 | D51: -12.9 | E51: - | F51: - | G51: -
A52: Total Dividends Paid | B52: - | C52: -11 | D52: -12.9 | E52: - | F52: -1.8 | G52: -7.1
A54: Special Dividend Paid | B54: - | C54: - | D54: - | E54: - | F54: - | G54: -
A55: Other Financing Activities | B55: -11.4 | C55: -50.6 | D55: -55.2 | E55: -1.5 | F55: -0.8 | G55: -1
A56: Cash from Financing | B56: -12.7 | C56: -62.5 | D56: 528.7 | E56: -6.5 | F56: -4.9 | G56: 35
A58: Foreign Exchange Rate Adj. | B58: -0.4 | C58: -4.5 | D58: -0.3 | E58: 1.4 | F58: - | G58: -1.3
A59: Net Change in Cash | B59: 0.5 | C59: -29.5 | D59: 10 | E59: 6.9 | F59: 8.8 | G59: 10.5
A61: Supplemental Items
A62: Cash Interest Paid | B62: NA | C62: NA | D62: NA | E62: 35.6 | F62: 35.3 | G62: 35.3
A63: Cash Taxes Paid | B63: NA | C63: NA | D63: NA | E63: 14 | F63: 13.1 | G63: 13.1
A64: Levered Free Cash Flow | B64: NA | C64: 33.8375 | D64: 50.8375 | E64: 10.525 | F64: 10.2375 | G64: 2.5
A65: Unlevered Free Cash Flow | B65: NA | C65: 36.9 | D65: 61.05 | E65: 37.3625 | F65: 35.575 | G65: 27.35
A66: Change in Net Working Capital | B66: NA | C66: 8.5 | D66: -13 | E66: 10.3 | F66: 2.8 | G66: 22.2
A67: Net Debt Issued | B67: -1.3 | C67: -0.9 | D67: 369.5 | E67: -5 | F67: -2.3 | G67: 43.1
A68: Filing Date | B68: 41088 | C68: 41348 | D68: 41712 | E68: 41712 | F68: 41712 | G68: 41957
A69: Restatement Type | B69: NCA | C69: NC | D69: RS | E69: NC | F69: O | G69: O
A70: Calculation Type | B70: REP | C70: REP | D70: REP | E70: REP | F70: REP | G70: LTM

Sheet Capital Structure Summary
A5: Dynacast International Inc. > Financials > Capital Structure Summary
A7: In Millions of the reported currency, except ratios and % of Total values. | B7: Restatement: | C7: Latest Filings | E7: Period Type: | F7: Annual
B8: Currency: | C8: Reported Currency | E8: Conversion: | F8: Today's Spot Rate
B9: Units: | C9: S&P Capital IQ (Default) | E9: Decimals: | F9: Capital IQ (Default)
B10: Order: | C10: Latest on Right
A13: Capital Structure Data
A14: For the Fiscal Period Ending | B14: 12 months Dec-31-2012 | D14: 12 months Dec-31-2013 | F14: 3 months Sep-30-2014
A15: Currency | B15: USD | D15: USD | F15: USD
A16: Units | B16: Millions | C16: % of Total | D16: Millions | E16: % of Total | F16: Millions | G16: % of Total
A18: Total Debt | B18: 445.5 | C18: 0.77789419 | D18: 443.3 | E18: 0.76788498 | F18: 486 | G18: 0.79554755
A19: Total Common Equity | B19: 123.4 | C19: 0.21547058 | D19: 129.9 | E19: 0.22501299 | F19: 120.7 | G19: 0.19757734
A20: Total Minority Interest | B20: 3.8 | C20: 0.0066352366 | D20: 4.1 | E20: 0.0071020267 | F20: 4.2 | G20: 0.0068751023
A21: Total Capital | B21: 572.7 | C21: 1 | D21: 577.3 | E21: 1 | F21: 610.9 | G21: 1
A24: Currency | B24: USD | D24: USD | F24: USD
A25: Exchange Rate | B25: 1 | D25: 1 | F25: 1
A26: Conversion Method | B26: S | D26: S | F26: S
A29: Debt Summary Data
A30: For the Fiscal Period Ending | B30: 12 months Dec-31-2012 | D30: 12 months Dec-31-2013 | F30: 3 months Sep-30-2014
A31: Currency | B31: USD | D31: USD | F31: USD
A32: Units | B32: Millions | C32: % of Total | D32: Millions | E32: % of Total | F32: Millions | G32: % of Total
A34: Total Revolving Credit | B34: - | C34: - | D34: 0 | E34: 0 | F34: 0 | G34: 0
A35: Total Term Loans | B35: 42.5 | C35: 0.095398 | D35: 40.3 | E35: 0.090909 | F35: 83 | G35: 0.170781
A36: Total Senior Bonds and Notes | B36: 350 | C36: 0.785634 | D36: 350 | E36: 0.789533 | F36: 350 | G36: 0.720164
A37: General/Other Borrowings | B37: 53 | C37: 0.118967 | D37: 53 | E37: 0.119557 | F37: 53 | G37: 0.109053
A38: Total Principal Due | B38: 445.5 | C38: 1 | D38: 443.3 | E38: 1 | F38: 486 | G38: 1
A40: Total Debt Outstanding | B40: 445.5 | C40: 1 | D40: 443.3 | E40: 1 | F40: 486 | G40: 1
A42: Available Credit
A43: Undrawn Revolving Credit | B43: - | C43: - | D43: 48.7 | E43: - | F43: 51.6 | G43: -
A44: Total Undrawn Credit | B44: - | C44: - | D44: 48.7 | E44: - | F44: 51.6 | G44: -
A46: Additional Totals
A47: Total Cash & ST Investments | B47: 28 | C47: - | D47: 36.8 | E47: - | F47: 40.3 | G47: -
A48: Net Debt | B48: 417.5 | C48: - | D48: 406.5 | E48: - | F48: 445.7 | G48: -
A49: Total Senior Debt | B49: 445.5 | C49: 1 | D49: 443.3 | E49: 1 | F49: 486 | G49: 1
A50: Total Convertible Debt | B50: 403 | C50: 0.904601 | D50: 403 | E50: 0.90909 | F50: 403 | G50: 0.829218
A51: Curr. Port. of LT Debt/Cap. Leases | B51: 6.3 | C51: 0.014141 | D51: 5.6 | E51: 0.012632 | F51: 19.5 | G51: 0.040123
A52: Long-Term Debt (Incl. Cap. Leases) | B52: 439.2 | C52: 0.985858 | D52: 437.7 | E52: 0.987367 | F52: 466.5 | G52: 0.959876
A53: Total Bank Debt | B53: 42.5 | C53: 0.095398 | D53: 40.3 | E53: 0.090909 | F53: 83 | G53: 0.170781
A54: Total Secured Debt | B54: 392.5 | C54: 0.881032 | D54: 384.4 | E54: 0.867132 | F54: 427.5 | G54: 0.879629
A55: Senior Secured Loans | B55: 42.5 | C55: 0.095398 | D55: 34.4 | E55: 0.077599 | F55: 77.5 | G55: 0.159465
A56: Senior Secured Bonds and Notes | B56: 350 | C56: 0.785634 | D56: 350 | E56: 0.789533 | F56: 350 | G56: 0.720164
A57: Total Senior Secured Debt | B57: 392.5 | C57: 0.881032 | D57: 384.4 | E57: 0.867132 | F57: 427.5 | G57: 0.879629
A58: Total Unsecured Debt | B58: 53 | C58: 0.118967 | D58: 58.9 | E58: 0.132867 | F58: 58.5 | G58: 0.12037
A59: Second Lien Bonds and Notes | B59: 350 | C59: 0.785634 | D59: 350 | E59: 0.789533 | F59: 350 | G59: 0.720164
A60: Second Lien Debt | B60: 350 | C60: 0.785634 | D60: 350 | E60: 0.789533 | F60: 350 | G60: 0.720164
... A62: Variable Rate Debt | B62: 42.5 | C62: 0.095398 | D62: 34.4 | E62: 0.077599 | F62: 77.5 | G62: 0.159465
A64: Credit Ratios
A65: Net Debt/EBITDA | B65: 4.552889 | C65: - | D65: 3.912415 | E65: - | F65: 3.417945 | G65: -
A66: Total Debt/EBITDA | B66: 4.858233 | C66: - | D66: 4.266602 | E66: - | F66: 3.726994 | G66: -
A67: Total Senior Debt/EBITDA | B67: 4.858233 | C67: - | D67: 4.266602 | E67: - | F67: 3.726994 | G67: -
A68: Total Senior Secured/EBITDA | B68: 4.280261 | C68: - | D68: 3.699711 | E68: - | F68: 3.278374 | G68: -
A69: Net Debt/(EBITDA-CAPEX) | B69: 5.989956 | C69: - | D69: 6.331775 | E69: - | F69: 4.474899 | G69: -
A70: Total Debt/(EBITDA-CAPEX) | B70: 6.391678 | C70: - | D70: 6.904984 | E70: - | F70: 4.879518 | G70: -
A71: Total Senior Debt/(EBITDA-CAPEX) | B71: 6.391678 | C71: - | D71: 6.904984 | E71: - | F71: 4.879518 | G71: -
A72: Total Senior Secured/(EBITDA-CAPEX) | B72: 5.631276 | C72: - | D72: 5.987538 | E72: - | F72: 4.292169 | G72: -
A74: Fixed Payment Schedule
A75: LT Debt (Incl. Cap. Leases) Due +1 | B75: 6.3 | C75: 0.014141414 | D75: 5.6 | E75: 0.012632529 | F75: - | G75: -
A76: LT Debt (Incl. Cap. Leases) Due +2 | B76: 7.5 | C76: 0.016835017 | D76: 17.7 | E76: 0.039927814 | F76: - | G76: -
A77: LT Debt (Incl. Cap. Leases) Due +3 | B77: 16.2 | C77: 0.036363636 | D77: 14 | E77: 0.031581322 | F77: - | G77: -
A78: LT Debt (Incl. Cap. Leases) Due +4 | B78: 12.5 | C78: 0.028058361 | D78: 1.5 | E78: 0.0033837131 | F78: - | G78: -
A79: LT Debt (Incl. Cap. Leases) Due +5 | B79: - | C79: - | D79: 1.5 | E79: 0.0033837131 | F79: - | G79: -
A80: LT Debt (Incl. Cap. Leases) Due, Next 5 Yrs | B80: 42.5 | C80: 0.095398429 | D80: 40.3 | E80: 0.090909091 | F80: - | G80: -
A81: LT Debt (Incl. Cap. Leases) Due, After 5 Yrs | B81: 350 | C81: 0.78563412 | D81: 350 | E81: 0.78953305 | F81: - | G81: -
A83: Operating Lease Commitment Due +1 | B83: 8.3 | C83: - | D83: 9.3 | E83: - | F83: - | G83: -
A84: Operating Lease Commitment Due +2 | B84: 7.3 | C84: - | D84: 8.8 | E84: - | F84: - | G84: -
A85: Operating Lease Commitment Due +3 | B85: 6.4 | C85: - | D85: 7.8 | E85: - | F85: - | G85: -
A86: Operating Lease Commitment Due +4 | B86: 5.6 | C86: - | D86: 6.5 | E86: - | F86: - | G86: -
A87: Operating Lease Commitment Due +5 | B87: 4.5 | C87: - | D87: 5.3 | E87: - | F87: - | G87: -
A88: Operating Lease Commitment Due, Next 5 Yrs | B88: 32.1 | C88: - | D88: 37.7 | E88: - | F88: - | G88: -
A89: Operating Lease Commitment Due, After 5 Yrs | B89: 20.7 | C89: - | D89: 34.7 | E89: - | F89: - | G89: -
A91: Contractual Obligations Due +1 | B91: 5.1 | C91: - | D91: 11.6 | E91: - | F91: - | G91: -
A92: Contractual Obligations Due + 2 | B92: 4.667 | C92: - | D92: 11.867 | E92: - | F92: - | G92: -
A93: Contractual Obligations Due + 3 | B93: 4.667 | C93: - | D93: 11.867 | E93: - | F93: - | G93: -
A94: Contractual Obligations Due + 4 | B94: 4.666 | C94: - | D94: 11.866 | E94: - | F94: - | G94: -
A95: Contractual Obligations Due + 5 | B95: 3.9 | C95: - | D95: 28.425 | E95: - | F95: - | G95: -
... A98: Total Contractual Obligations | B98: 250.2 | C98: - | D98: 165.4 | E98: - | F98: - | G98: -
A100: Interest Rate Data
A101: Filing Date | B101: 41712 | C101: - | D101: 41712 | E101: - | F101: 41957 | G101: -
A103: Currency | B103: USD | D103: USD | F103: USD
A104: Exchange Rate | B104: 1 | D104: 1 | F104: 1
A105: Conversion Method | B105: S | D105: S | F105: S

Sheet Quick IRR rule of thumb
B3: Quick Approx IRRs
B4: MOIC | C4: TIME | D4: IRR
B5: 2 | C5: 1 | D5: 1
B6: 2 | C6: 2 | D6: 0.4
B7: 2 | C7: 3 | D7: 0.25
B8: 2 | C8: 4 | D8: 0.2
B9: 2 | C9: 5 | D9: 0.15
B11: Quick Approx IRRs
B12: MOIC | C12: TIME | D12: IRR
B13: 3 | C13: 3 | D13: 0.45
B14: 3 | C14: 5 | D14: 0.25
B16: Quick Approx IRRs
B17: MOIC | C17: TIME | D17: IRR
B18: 2 | C18: 3 | D18: 0.25
B19: 2.5 | C19: 3 | D19: 0.35
B20: 3 | C20: 3 | D20: 0.45
B22: Quick Approx IRRs
B23: MOIC | C23: TIME | D23: IRR
B24: 2 | C24: 5 | D24: 0.15
B25: 2.5 | C25: 5 | D25: 0.2
B26: 3 | C26: 5 | D26: 0.25
